<?xml version='1.0' encoding='UTF-8'?>
<Track Version="1.0" UUID="4c169925-474f-42c0-8bec-ff2cd2ab4e94" Timestamp="2021-07-01T22:00:37.620051+00:00" Source="SSE">
  <TrackPoint Age="0.0000" Stage="MS" M="4.0000" logL="2.4185" logR="0.3249" logT="4.2054" Mc="0.0000" Menv="1.0000E-10" Spin="5.1109E+03" Z="0.01"/>
  <TrackPoint Age="8.5245" Stage="MS" M="4.0000" logL="2.4275" logR="0.3361" logT="4.2021" Mc="0.0000" Menv="1.0000E-10" Spin="4.9646E+03" Z="?"/>
  <TrackPoint Age="17.0490" Stage="MS" M="4.0000" logL="2.4374" logR="0.3475" logT="4.1989" Mc="0.0000" Menv="1.0000E-10" Spin="4.8197E+03" Z="?"/>
  <TrackPoint Age="25.5734" Stage="MS" M="4.0000" logL="2.4480" logR="0.3590" logT="4.1958" Mc="0.0000" Menv="1.0000E-10" Spin="4.6753E+03" Z="?"/>
  <TrackPoint Age="34.0979" Stage="MS" M="4.0000" logL="2.4594" logR="0.3708" logT="4.1927" Mc="0.0000" Menv="1.0000E-10" Spin="4.5302E+03" Z="?"/>
  <TrackPoint Age="42.6224" Stage="MS" M="4.0000" logL="2.4717" logR="0.3830" logT="4.1897" Mc="0.0000" Menv="1.0000E-10" Spin="4.3838E+03" Z="?"/>
  <TrackPoint Age="51.1469" Stage="MS" M="4.0000" logL="2.4848" logR="0.3956" logT="4.1867" Mc="0.0000" Menv="1.0000E-10" Spin="4.2351E+03" Z="?"/>
  <TrackPoint Age="59.6714" Stage="MS" M="4.0000" logL="2.4987" logR="0.4088" logT="4.1836" Mc="0.0000" Menv="1.0000E-10" Spin="4.0834E+03" Z="?"/>
  <TrackPoint Age="68.1958" Stage="MS" M="4.0000" logL="2.5133" logR="0.4226" logT="4.1803" Mc="0.0000" Menv="1.0000E-10" Spin="3.9283E+03" Z="?"/>
  <TrackPoint Age="76.7203" Stage="MS" M="4.0000" logL="2.5289" logR="0.4371" logT="4.1769" Mc="0.0000" Menv="1.0000E-10" Spin="3.7690E+03" Z="?"/>
  <TrackPoint Age="85.2448" Stage="MS" M="4.0000" logL="2.5452" logR="0.4526" logT="4.1733" Mc="0.0000" Menv="1.0000E-10" Spin="3.6051E+03" Z="?"/>
  <TrackPoint Age="93.7693" Stage="MS" M="4.0000" logL="2.5623" logR="0.4691" logT="4.1693" Mc="0.0000" Menv="1.0000E-10" Spin="3.4359E+03" Z="?"/>
  <TrackPoint Age="102.2938" Stage="MS" M="4.0000" logL="2.5802" logR="0.4868" logT="4.1650" Mc="0.0000" Menv="1.0000E-10" Spin="3.2602E+03" Z="?"/>
  <TrackPoint Age="110.8183" Stage="MS" M="4.0000" logL="2.5990" logR="0.5060" logT="4.1600" Mc="0.0000" Menv="1.0000E-10" Spin="3.0765E+03" Z="?"/>
  <TrackPoint Age="119.3427" Stage="MS" M="4.0000" logL="2.6185" logR="0.5273" logT="4.1542" Mc="0.0000" Menv="1.0000E-10" Spin="2.8821E+03" Z="?"/>
  <TrackPoint Age="127.8672" Stage="MS" M="4.0000" logL="2.6389" logR="0.5515" logT="4.1472" Mc="0.0000" Menv="1.0000E-10" Spin="2.6729E+03" Z="?"/>
  <TrackPoint Age="136.3917" Stage="MS" M="4.0000" logL="2.6601" logR="0.5797" logT="4.1384" Mc="0.0000" Menv="1.0000E-10" Spin="2.4430E+03" Z="?"/>
  <TrackPoint Age="144.9162" Stage="MS" M="4.0000" logL="2.6821" logR="0.6140" logT="4.1268" Mc="0.0000" Menv="1.0000E-10" Spin="2.1852E+03" Z="?"/>
  <TrackPoint Age="153.0312" Stage="MS" M="4.0000" logL="2.7038" logR="0.6548" logT="4.1118" Mc="0.0000" Menv="1.0000E-10" Spin="1.9065E+03" Z="?"/>
  <TrackPoint Age="159.4170" Stage="MS" M="4.0000" logL="2.7214" logR="0.6949" logT="4.0962" Mc="0.0000" Menv="1.0000E-10" Spin="1.6612E+03" Z="?"/>
  <TrackPoint Age="164.6229" Stage="MS" M="4.0000" logL="2.7361" logR="0.7347" logT="4.0800" Mc="0.0000" Menv="1.0000E-10" Spin="1.4444E+03" Z="?"/>
  <TrackPoint Age="170.4896" Stage="HG" M="4.0000" logL="2.8496" logR="0.6914" logT="4.1300" Mc="0.6233" Menv="1.0000E-10" Spin="1.9901E+03" Z="?"/>
  <TrackPoint Age="170.5330" Stage="HG" M="4.0000" logL="2.8394" logR="0.7306" logT="4.1078" Mc="0.6240" Menv="1.0000E-10" Spin="1.7350E+03" Z="?"/>
  <TrackPoint Age="170.5763" Stage="HG" M="4.0000" logL="2.8292" logR="0.7698" logT="4.0857" Mc="0.6246" Menv="1.0000E-10" Spin="1.5079E+03" Z="?"/>
  <TrackPoint Age="170.6196" Stage="HG" M="4.0000" logL="2.8191" logR="0.8089" logT="4.0636" Mc="0.6252" Menv="1.0000E-10" Spin="1.3068E+03" Z="?"/>
  <TrackPoint Age="170.6629" Stage="HG" M="4.0000" logL="2.8089" logR="0.8481" logT="4.0414" Mc="0.6259" Menv="1.0000E-10" Spin="1.1295E+03" Z="?"/>
  <TrackPoint Age="170.7063" Stage="HG" M="4.0000" logL="2.7988" logR="0.8873" logT="4.0193" Mc="0.6265" Menv="1.0000E-10" Spin="9.7380E+02" Z="?"/>
  <TrackPoint Age="170.7496" Stage="HG" M="3.9999" logL="2.7886" logR="0.9265" logT="3.9972" Mc="0.6272" Menv="1.0000E-10" Spin="8.3767E+02" Z="?"/>
  <TrackPoint Age="170.7929" Stage="HG" M="3.9999" logL="2.7785" logR="0.9657" logT="3.9751" Mc="0.6278" Menv="1.0000E-10" Spin="7.1905E+02" Z="?"/>
  <TrackPoint Age="170.8363" Stage="HG" M="3.9999" logL="2.7683" logR="1.0048" logT="3.9529" Mc="0.6284" Menv="1.0000E-10" Spin="6.1604E+02" Z="?"/>
  <TrackPoint Age="170.8796" Stage="HG" M="3.9999" logL="2.7581" logR="1.0440" logT="3.9308" Mc="0.6291" Menv="1.0000E-10" Spin="5.2687E+02" Z="?"/>
  <TrackPoint Age="170.9229" Stage="HG" M="3.9999" logL="2.7480" logR="1.0832" logT="3.9087" Mc="0.6297" Menv="1.0000E-10" Spin="4.4988E+02" Z="?"/>
  <TrackPoint Age="170.9663" Stage="HG" M="3.9999" logL="2.7378" logR="1.1224" logT="3.8865" Mc="0.6303" Menv="1.0000E-10" Spin="3.8359E+02" Z="?"/>
  <TrackPoint Age="171.0096" Stage="HG" M="3.9999" logL="2.7277" logR="1.1615" logT="3.8644" Mc="0.6310" Menv="1.0000E-10" Spin="3.2664E+02" Z="?"/>
  <TrackPoint Age="171.0529" Stage="HG" M="3.9998" logL="2.7175" logR="1.2007" logT="3.8423" Mc="0.6316" Menv="1.0000E-10" Spin="2.7782E+02" Z="?"/>
  <TrackPoint Age="171.0963" Stage="HG" M="3.9998" logL="2.7074" logR="1.2399" logT="3.8202" Mc="0.6323" Menv="1.0000E-10" Spin="2.3604E+02" Z="?"/>
  <TrackPoint Age="171.1396" Stage="HG" M="3.9998" logL="2.6972" logR="1.2791" logT="3.7980" Mc="0.6329" Menv="1.0000E-10" Spin="2.0036E+02" Z="?"/>
  <TrackPoint Age="171.1829" Stage="HG" M="3.9998" logL="2.6870" logR="1.3182" logT="3.7759" Mc="0.6335" Menv="3.7893E-08" Spin="1.6990E+02" Z="?"/>
  <TrackPoint Age="171.2263" Stage="HG" M="3.9998" logL="2.6769" logR="1.3574" logT="3.7538" Mc="0.6342" Menv="1.7767E-03" Spin="1.3173E+02" Z="?"/>
  <TrackPoint Age="171.2696" Stage="HG" M="3.9997" logL="2.6667" logR="1.3966" logT="3.7317" Mc="0.6348" Menv="4.7548E-02" Spin="7.2548E+01" Z="?"/>
  <TrackPoint Age="171.3130" Stage="HG" M="3.9997" logL="2.6565" logR="1.4358" logT="3.7095" Mc="0.6354" Menv="3.6950E-01" Spin="3.0647E+01" Z="?"/>
  <TrackPoint Age="171.3563" Stage="HG" M="3.9997" logL="2.6464" logR="1.4749" logT="3.6874" Mc="0.6361" Menv="1.6813E+00" Spin="1.2531E+01" Z="?"/>
  <TrackPoint Age="171.3563" Stage="FGB" M="3.9997" logL="2.6464" logR="1.4749" logT="3.6874" Mc="0.6361" Menv="1.6818E+00" Spin="1.2528E+01" Z="?"/>
  <TrackPoint Age="171.3647" Stage="FGB" M="3.9997" logL="2.6518" logR="1.4786" logT="3.6869" Mc="0.6362" Menv="1.7029E+00" Spin="1.2295E+01" Z="?"/>
  <TrackPoint Age="171.3731" Stage="FGB" M="3.9997" logL="2.6573" logR="1.4822" logT="3.6865" Mc="0.6364" Menv="1.7242E+00" Spin="1.2066E+01" Z="?"/>
  <TrackPoint Age="171.3813" Stage="FGB" M="3.9997" logL="2.6627" logR="1.4858" logT="3.6860" Mc="0.6365" Menv="1.7456E+00" Spin="1.1842E+01" Z="?"/>
  <TrackPoint Age="171.3895" Stage="FGB" M="3.9997" logL="2.6682" logR="1.4895" logT="3.6856" Mc="0.6366" Menv="1.7671E+00" Spin="1.1622E+01" Z="?"/>
  <TrackPoint Age="171.3976" Stage="FGB" M="3.9997" logL="2.6737" logR="1.4931" logT="3.6851" Mc="0.6368" Menv="1.7887E+00" Spin="1.1406E+01" Z="?"/>
  <TrackPoint Age="171.4056" Stage="FGB" M="3.9997" logL="2.6791" logR="1.4968" logT="3.6847" Mc="0.6369" Menv="1.8105E+00" Spin="1.1195E+01" Z="?"/>
  <TrackPoint Age="171.4136" Stage="FGB" M="3.9997" logL="2.6846" logR="1.5004" logT="3.6842" Mc="0.6370" Menv="1.8323E+00" Spin="1.0988E+01" Z="?"/>
  <TrackPoint Age="171.4214" Stage="FGB" M="3.9996" logL="2.6900" logR="1.5040" logT="3.6838" Mc="0.6372" Menv="1.8543E+00" Spin="1.0785E+01" Z="?"/>
  <TrackPoint Age="171.4292" Stage="FGB" M="3.9996" logL="2.6955" logR="1.5077" logT="3.6833" Mc="0.6373" Menv="1.8764E+00" Spin="1.0586E+01" Z="?"/>
  <TrackPoint Age="171.4369" Stage="FGB" M="3.9996" logL="2.7009" logR="1.5113" logT="3.6828" Mc="0.6374" Menv="1.8986E+00" Spin="1.0391E+01" Z="?"/>
  <TrackPoint Age="171.4445" Stage="FGB" M="3.9996" logL="2.7064" logR="1.5150" logT="3.6824" Mc="0.6376" Menv="1.9209E+00" Spin="1.0200E+01" Z="?"/>
  <TrackPoint Age="171.4521" Stage="FGB" M="3.9996" logL="2.7119" logR="1.5186" logT="3.6819" Mc="0.6377" Menv="1.9434E+00" Spin="1.0012E+01" Z="?"/>
  <TrackPoint Age="171.4595" Stage="FGB" M="3.9996" logL="2.7173" logR="1.5223" logT="3.6815" Mc="0.6378" Menv="1.9659E+00" Spin="9.8285E+00" Z="?"/>
  <TrackPoint Age="171.4669" Stage="FGB" M="3.9996" logL="2.7228" logR="1.5259" logT="3.6810" Mc="0.6379" Menv="1.9885E+00" Spin="9.6482E+00" Z="?"/>
  <TrackPoint Age="171.4742" Stage="FGB" M="3.9996" logL="2.7282" logR="1.5296" logT="3.6805" Mc="0.6381" Menv="2.0113E+00" Spin="9.4715E+00" Z="?"/>
  <TrackPoint Age="171.4815" Stage="FGB" M="3.9996" logL="2.7337" logR="1.5332" logT="3.6801" Mc="0.6382" Menv="2.0341E+00" Spin="9.2981E+00" Z="?"/>
  <TrackPoint Age="171.4887" Stage="FGB" M="3.9996" logL="2.7391" logR="1.5369" logT="3.6796" Mc="0.6383" Menv="2.0570E+00" Spin="9.1281E+00" Z="?"/>
  <TrackPoint Age="171.4958" Stage="FGB" M="3.9996" logL="2.7446" logR="1.5405" logT="3.6791" Mc="0.6384" Menv="2.0800E+00" Spin="8.9614E+00" Z="?"/>
  <TrackPoint Age="171.5028" Stage="FGB" M="3.9996" logL="2.7500" logR="1.5442" logT="3.6787" Mc="0.6385" Menv="2.1031E+00" Spin="8.7979E+00" Z="?"/>
  <TrackPoint Age="171.5098" Stage="FGB" M="3.9996" logL="2.7555" logR="1.5479" logT="3.6782" Mc="0.6387" Menv="2.1262E+00" Spin="8.6376E+00" Z="?"/>
  <TrackPoint Age="171.5166" Stage="FGB" M="3.9996" logL="2.7610" logR="1.5515" logT="3.6777" Mc="0.6388" Menv="2.1494E+00" Spin="8.4803E+00" Z="?"/>
  <TrackPoint Age="171.5235" Stage="FGB" M="3.9996" logL="2.7664" logR="1.5552" logT="3.6773" Mc="0.6389" Menv="2.1727E+00" Spin="8.3261E+00" Z="?"/>
  <TrackPoint Age="171.5302" Stage="FGB" M="3.9995" logL="2.7719" logR="1.5588" logT="3.6768" Mc="0.6390" Menv="2.1961E+00" Spin="8.1749E+00" Z="?"/>
  <TrackPoint Age="171.5369" Stage="FGB" M="3.9995" logL="2.7773" logR="1.5625" logT="3.6763" Mc="0.6391" Menv="2.2195E+00" Spin="8.0265E+00" Z="?"/>
  <TrackPoint Age="171.5435" Stage="FGB" M="3.9995" logL="2.7828" logR="1.5662" logT="3.6759" Mc="0.6392" Menv="2.2429E+00" Spin="7.8810E+00" Z="?"/>
  <TrackPoint Age="171.5501" Stage="FGB" M="3.9995" logL="2.7882" logR="1.5698" logT="3.6754" Mc="0.6393" Menv="2.2664E+00" Spin="7.7383E+00" Z="?"/>
  <TrackPoint Age="171.5566" Stage="FGB" M="3.9995" logL="2.7937" logR="1.5735" logT="3.6749" Mc="0.6395" Menv="2.2900E+00" Spin="7.5983E+00" Z="?"/>
  <TrackPoint Age="171.5630" Stage="FGB" M="3.9995" logL="2.7991" logR="1.5772" logT="3.6745" Mc="0.6396" Menv="2.3136E+00" Spin="7.4610E+00" Z="?"/>
  <TrackPoint Age="171.5694" Stage="FGB" M="3.9995" logL="2.8046" logR="1.5809" logT="3.6740" Mc="0.6397" Menv="2.3372E+00" Spin="7.3263E+00" Z="?"/>
  <TrackPoint Age="171.5757" Stage="FGB" M="3.9995" logL="2.8101" logR="1.5845" logT="3.6735" Mc="0.6398" Menv="2.3608E+00" Spin="7.1942E+00" Z="?"/>
  <TrackPoint Age="171.5819" Stage="FGB" M="3.9995" logL="2.8155" logR="1.5882" logT="3.6730" Mc="0.6399" Menv="2.3845E+00" Spin="7.0646E+00" Z="?"/>
  <TrackPoint Age="171.5881" Stage="FGB" M="3.9995" logL="2.8210" logR="1.5919" logT="3.6726" Mc="0.6400" Menv="2.4081E+00" Spin="6.9374E+00" Z="?"/>
  <TrackPoint Age="171.5942" Stage="FGB" M="3.9995" logL="2.8264" logR="1.5955" logT="3.6721" Mc="0.6401" Menv="2.4318E+00" Spin="6.8127E+00" Z="?"/>
  <TrackPoint Age="171.6002" Stage="FGB" M="3.9995" logL="2.8319" logR="1.5992" logT="3.6716" Mc="0.6402" Menv="2.4554E+00" Spin="6.6903E+00" Z="?"/>
  <TrackPoint Age="171.6062" Stage="FGB" M="3.9995" logL="2.8373" logR="1.6029" logT="3.6712" Mc="0.6403" Menv="2.4791E+00" Spin="6.5702E+00" Z="?"/>
  <TrackPoint Age="171.6121" Stage="FGB" M="3.9994" logL="2.8428" logR="1.6066" logT="3.6707" Mc="0.6404" Menv="2.5027E+00" Spin="6.4524E+00" Z="?"/>
  <TrackPoint Age="171.6180" Stage="FGB" M="3.9994" logL="2.8483" logR="1.6103" logT="3.6702" Mc="0.6405" Menv="2.5263E+00" Spin="6.3368E+00" Z="?"/>
  <TrackPoint Age="171.6238" Stage="FGB" M="3.9994" logL="2.8537" logR="1.6139" logT="3.6697" Mc="0.6406" Menv="2.5498E+00" Spin="6.2234E+00" Z="?"/>
  <TrackPoint Age="171.6296" Stage="FGB" M="3.9994" logL="2.8592" logR="1.6176" logT="3.6692" Mc="0.6407" Menv="2.5733E+00" Spin="6.1121E+00" Z="?"/>
  <TrackPoint Age="171.6353" Stage="FGB" M="3.9994" logL="2.8646" logR="1.6213" logT="3.6688" Mc="0.6408" Menv="2.5968E+00" Spin="6.0030E+00" Z="?"/>
  <TrackPoint Age="171.6409" Stage="FGB" M="3.9994" logL="2.8701" logR="1.6250" logT="3.6683" Mc="0.6409" Menv="2.6201E+00" Spin="5.8958E+00" Z="?"/>
  <TrackPoint Age="171.6465" Stage="FGB" M="3.9994" logL="2.8755" logR="1.6287" logT="3.6678" Mc="0.6410" Menv="2.6434E+00" Spin="5.7907E+00" Z="?"/>
  <TrackPoint Age="171.6520" Stage="FGB" M="3.9994" logL="2.8810" logR="1.6324" logT="3.6673" Mc="0.6411" Menv="2.6666E+00" Spin="5.6875E+00" Z="?"/>
  <TrackPoint Age="171.6575" Stage="FGB" M="3.9994" logL="2.8864" logR="1.6361" logT="3.6668" Mc="0.6412" Menv="2.6897E+00" Spin="5.5863E+00" Z="?"/>
  <TrackPoint Age="171.6629" Stage="FGB" M="3.9994" logL="2.8919" logR="1.6398" logT="3.6664" Mc="0.6413" Menv="2.7127E+00" Spin="5.4870E+00" Z="?"/>
  <TrackPoint Age="171.6682" Stage="FGB" M="3.9994" logL="2.8974" logR="1.6435" logT="3.6659" Mc="0.6413" Menv="2.7356E+00" Spin="5.3895E+00" Z="?"/>
  <TrackPoint Age="171.6736" Stage="FGB" M="3.9994" logL="2.9028" logR="1.6471" logT="3.6654" Mc="0.6414" Menv="2.7584E+00" Spin="5.2938E+00" Z="?"/>
  <TrackPoint Age="171.6788" Stage="FGB" M="3.9993" logL="2.9083" logR="1.6508" logT="3.6649" Mc="0.6415" Menv="2.7809E+00" Spin="5.1999E+00" Z="?"/>
  <TrackPoint Age="171.6840" Stage="FGB" M="3.9993" logL="2.9137" logR="1.6545" logT="3.6644" Mc="0.6416" Menv="2.8034E+00" Spin="5.1077E+00" Z="?"/>
  <TrackPoint Age="171.6891" Stage="FGB" M="3.9993" logL="2.9192" logR="1.6582" logT="3.6639" Mc="0.6417" Menv="2.8256E+00" Spin="5.0173E+00" Z="?"/>
  <TrackPoint Age="171.6942" Stage="FGB" M="3.9993" logL="2.9246" logR="1.6619" logT="3.6635" Mc="0.6418" Menv="2.8477E+00" Spin="4.9285E+00" Z="?"/>
  <TrackPoint Age="171.6993" Stage="FGB" M="3.9993" logL="2.9301" logR="1.6656" logT="3.6630" Mc="0.6419" Menv="2.8696E+00" Spin="4.8414E+00" Z="?"/>
  <TrackPoint Age="171.7043" Stage="FGB" M="3.9993" logL="2.9355" logR="1.6693" logT="3.6625" Mc="0.6420" Menv="2.8912E+00" Spin="4.7558E+00" Z="?"/>
  <TrackPoint Age="171.7092" Stage="FGB" M="3.9993" logL="2.9410" logR="1.6730" logT="3.6620" Mc="0.6420" Menv="2.9127E+00" Spin="4.6719E+00" Z="?"/>
  <TrackPoint Age="171.7141" Stage="FGB" M="3.9993" logL="2.9465" logR="1.6767" logT="3.6615" Mc="0.6421" Menv="2.9339E+00" Spin="4.5895E+00" Z="?"/>
  <TrackPoint Age="171.7190" Stage="FGB" M="3.9993" logL="2.9519" logR="1.6804" logT="3.6610" Mc="0.6422" Menv="2.9548E+00" Spin="4.5086E+00" Z="?"/>
  <TrackPoint Age="171.7238" Stage="FGB" M="3.9993" logL="2.9574" logR="1.6841" logT="3.6605" Mc="0.6423" Menv="2.9754E+00" Spin="4.4292E+00" Z="?"/>
  <TrackPoint Age="171.7285" Stage="FGB" M="3.9992" logL="2.9628" logR="1.6879" logT="3.6600" Mc="0.6424" Menv="2.9958E+00" Spin="4.3513E+00" Z="?"/>
  <TrackPoint Age="171.7332" Stage="FGB" M="3.9992" logL="2.9683" logR="1.6916" logT="3.6596" Mc="0.6424" Menv="3.0158E+00" Spin="4.2748E+00" Z="?"/>
  <TrackPoint Age="171.7379" Stage="FGB" M="3.9992" logL="2.9737" logR="1.6953" logT="3.6591" Mc="0.6425" Menv="3.0355E+00" Spin="4.1997E+00" Z="?"/>
  <TrackPoint Age="171.7425" Stage="FGB" M="3.9992" logL="2.9792" logR="1.6990" logT="3.6586" Mc="0.6426" Menv="3.0548E+00" Spin="4.1260E+00" Z="?"/>
  <TrackPoint Age="171.7471" Stage="FGB" M="3.9992" logL="2.9847" logR="1.7027" logT="3.6581" Mc="0.6427" Menv="3.0738E+00" Spin="4.0536E+00" Z="?"/>
  <TrackPoint Age="171.7516" Stage="FGB" M="3.9992" logL="2.9901" logR="1.7064" logT="3.6576" Mc="0.6428" Menv="3.0924E+00" Spin="3.9825E+00" Z="?"/>
  <TrackPoint Age="171.7561" Stage="FGB" M="3.9992" logL="2.9956" logR="1.7101" logT="3.6571" Mc="0.6428" Menv="3.1105E+00" Spin="3.9127E+00" Z="?"/>
  <TrackPoint Age="171.7605" Stage="FGB" M="3.9992" logL="3.0010" logR="1.7138" logT="3.6566" Mc="0.6429" Menv="3.1283E+00" Spin="3.8443E+00" Z="?"/>
  <TrackPoint Age="171.7649" Stage="FGB" M="3.9992" logL="3.0065" logR="1.7176" logT="3.6561" Mc="0.6430" Menv="3.1455E+00" Spin="3.7770E+00" Z="?"/>
  <TrackPoint Age="171.7692" Stage="FGB" M="3.9991" logL="3.0119" logR="1.7213" logT="3.6556" Mc="0.6431" Menv="3.1623E+00" Spin="3.7110E+00" Z="?"/>
  <TrackPoint Age="171.7735" Stage="FGB" M="3.9991" logL="3.0174" logR="1.7250" logT="3.6551" Mc="0.6431" Menv="3.1786E+00" Spin="3.6462E+00" Z="?"/>
  <TrackPoint Age="171.7778" Stage="FGB" M="3.9991" logL="3.0228" logR="1.7287" logT="3.6546" Mc="0.6432" Menv="3.1944E+00" Spin="3.5825E+00" Z="?"/>
  <TrackPoint Age="171.7820" Stage="FGB" M="3.9991" logL="3.0283" logR="1.7324" logT="3.6541" Mc="0.6433" Menv="3.2096E+00" Spin="3.5200E+00" Z="?"/>
  <TrackPoint Age="171.7861" Stage="FGB" M="3.9991" logL="3.0338" logR="1.7361" logT="3.6536" Mc="0.6433" Menv="3.2242E+00" Spin="3.4586E+00" Z="?"/>
  <TrackPoint Age="171.7903" Stage="FGB" M="3.9991" logL="3.0392" logR="1.7399" logT="3.6531" Mc="0.6434" Menv="3.2382E+00" Spin="3.3984E+00" Z="?"/>
  <TrackPoint Age="171.7944" Stage="FGB" M="3.9991" logL="3.0447" logR="1.7436" logT="3.6526" Mc="0.6435" Menv="3.2516E+00" Spin="3.3392E+00" Z="?"/>
  <TrackPoint Age="171.7984" Stage="FGB" M="3.9991" logL="3.0501" logR="1.7473" logT="3.6521" Mc="0.6435" Menv="3.2643E+00" Spin="3.2811E+00" Z="?"/>
  <TrackPoint Age="171.8024" Stage="FGB" M="3.9990" logL="3.0556" logR="1.7510" logT="3.6516" Mc="0.6436" Menv="3.2763E+00" Spin="3.2241E+00" Z="?"/>
  <TrackPoint Age="171.8064" Stage="FGB" M="3.9990" logL="3.0610" logR="1.7548" logT="3.6511" Mc="0.6437" Menv="3.2876E+00" Spin="3.1680E+00" Z="?"/>
  <TrackPoint Age="171.8103" Stage="FGB" M="3.9990" logL="3.0665" logR="1.7585" logT="3.6506" Mc="0.6437" Menv="3.2982E+00" Spin="3.1130E+00" Z="?"/>
  <TrackPoint Age="171.8142" Stage="FGB" M="3.9990" logL="3.0719" logR="1.7622" logT="3.6501" Mc="0.6438" Menv="3.3079E+00" Spin="3.0590E+00" Z="?"/>
  <TrackPoint Age="171.8180" Stage="FGB" M="3.9990" logL="3.0774" logR="1.7660" logT="3.6496" Mc="0.6439" Menv="3.3168E+00" Spin="3.0059E+00" Z="?"/>
  <TrackPoint Age="171.8219" Stage="FGB" M="3.9990" logL="3.0829" logR="1.7697" logT="3.6491" Mc="0.6439" Menv="3.3249E+00" Spin="2.9538E+00" Z="?"/>
  <TrackPoint Age="171.8256" Stage="FGB" M="3.9990" logL="3.0883" logR="1.7734" logT="3.6486" Mc="0.6440" Menv="3.3321E+00" Spin="2.9026E+00" Z="?"/>
  <TrackPoint Age="171.8294" Stage="FGB" M="3.9990" logL="3.0938" logR="1.7772" logT="3.6481" Mc="0.6441" Menv="3.3384E+00" Spin="2.8524E+00" Z="?"/>
  <TrackPoint Age="171.8331" Stage="FGB" M="3.9989" logL="3.0992" logR="1.7809" logT="3.6476" Mc="0.6441" Menv="3.3437E+00" Spin="2.8030E+00" Z="?"/>
  <TrackPoint Age="171.8367" Stage="FGB" M="3.9989" logL="3.1047" logR="1.7846" logT="3.6471" Mc="0.6442" Menv="3.3480E+00" Spin="2.7545E+00" Z="?"/>
  <TrackPoint Age="171.8403" Stage="FGB" M="3.9989" logL="3.1101" logR="1.7884" logT="3.6466" Mc="0.6443" Menv="3.3512E+00" Spin="2.7069E+00" Z="?"/>
  <TrackPoint Age="171.8439" Stage="FGB" M="3.9989" logL="3.1156" logR="1.7921" logT="3.6461" Mc="0.6443" Menv="3.3534E+00" Spin="2.6601E+00" Z="?"/>
  <TrackPoint Age="171.8475" Stage="FGB" M="3.9989" logL="3.1211" logR="1.7959" logT="3.6456" Mc="0.6444" Menv="3.3544E+00" Spin="2.6142E+00" Z="?"/>
  <TrackPoint Age="171.8510" Stage="FGB" M="3.9989" logL="3.1265" logR="1.7996" logT="3.6451" Mc="0.6444" Menv="3.3544E+00" Spin="2.5691E+00" Z="?"/>
  <TrackPoint Age="171.8545" Stage="FGB" M="3.9989" logL="3.1320" logR="1.8033" logT="3.6446" Mc="0.6445" Menv="3.3544E+00" Spin="2.5248E+00" Z="?"/>
  <TrackPoint Age="171.8579" Stage="FGB" M="3.9988" logL="3.1374" logR="1.8071" logT="3.6441" Mc="0.6446" Menv="3.3543E+00" Spin="2.4812E+00" Z="?"/>
  <TrackPoint Age="171.8613" Stage="FGB" M="3.9988" logL="3.1429" logR="1.8108" logT="3.6436" Mc="0.6446" Menv="3.3542E+00" Spin="2.4385E+00" Z="?"/>
  <TrackPoint Age="171.8647" Stage="FGB" M="3.9988" logL="3.1483" logR="1.8146" logT="3.6431" Mc="0.6447" Menv="3.3541E+00" Spin="2.3965E+00" Z="?"/>
  <TrackPoint Age="171.8680" Stage="FGB" M="3.9988" logL="3.1538" logR="1.8183" logT="3.6426" Mc="0.6447" Menv="3.3541E+00" Spin="2.3552E+00" Z="?"/>
  <TrackPoint Age="171.8714" Stage="FGB" M="3.9988" logL="3.1592" logR="1.8221" logT="3.6421" Mc="0.6448" Menv="3.3540E+00" Spin="2.3147E+00" Z="?"/>
  <TrackPoint Age="171.8746" Stage="FGB" M="3.9988" logL="3.1647" logR="1.8258" logT="3.6415" Mc="0.6448" Menv="3.3539E+00" Spin="2.2749E+00" Z="?"/>
  <TrackPoint Age="171.8779" Stage="FGB" M="3.9988" logL="3.1702" logR="1.8296" logT="3.6410" Mc="0.6449" Menv="3.3539E+00" Spin="2.2358E+00" Z="?"/>
  <TrackPoint Age="171.8811" Stage="FGB" M="3.9987" logL="3.1756" logR="1.8333" logT="3.6405" Mc="0.6449" Menv="3.3538E+00" Spin="2.1973E+00" Z="?"/>
  <TrackPoint Age="171.8823" Stage="CHeB" M="3.9987" logL="3.1777" logR="1.8347" logT="3.6403" Mc="0.6450" Menv="3.3538E+00" Spin="2.1831E+00" Z="?"/>
  <TrackPoint Age="172.1723" Stage="CHeB" M="3.9972" logL="3.1375" logR="1.8072" logT="3.6440" Mc="0.6482" Menv="3.3490E+00" Spin="2.4790E+00" Z="?"/>
  <TrackPoint Age="172.4624" Stage="CHeB" M="3.9960" logL="3.0998" logR="1.7814" logT="3.6475" Mc="0.6515" Menv="3.3444E+00" Spin="2.7944E+00" Z="?"/>
  <TrackPoint Age="172.7524" Stage="CHeB" M="3.9949" logL="3.0645" logR="1.7573" logT="3.6507" Mc="0.6548" Menv="3.3401E+00" Spin="3.1275E+00" Z="?"/>
  <TrackPoint Age="173.0425" Stage="CHeB" M="3.9939" logL="3.0317" logR="1.7349" logT="3.6537" Mc="0.6581" Menv="3.3358E+00" Spin="3.4759E+00" Z="?"/>
  <TrackPoint Age="173.3325" Stage="CHeB" M="3.9930" logL="3.0011" logR="1.7141" logT="3.6565" Mc="0.6613" Menv="3.3317E+00" Spin="3.8367E+00" Z="?"/>
  <TrackPoint Age="173.6226" Stage="CHeB" M="3.9923" logL="2.9727" logR="1.6948" logT="3.6590" Mc="0.6646" Menv="3.3277E+00" Spin="4.2071E+00" Z="?"/>
  <TrackPoint Age="173.9126" Stage="CHeB" M="3.9916" logL="2.9464" logR="1.6770" logT="3.6614" Mc="0.6679" Menv="3.3237E+00" Spin="4.5835E+00" Z="?"/>
  <TrackPoint Age="174.2027" Stage="CHeB" M="3.9910" logL="2.9222" logR="1.6606" logT="3.6635" Mc="0.6712" Menv="3.3198E+00" Spin="4.9625E+00" Z="?"/>
  <TrackPoint Age="174.4927" Stage="CHeB" M="3.9904" logL="2.8999" logR="1.6455" logT="3.6655" Mc="0.6744" Menv="3.3160E+00" Spin="5.3403E+00" Z="?"/>
  <TrackPoint Age="174.7828" Stage="CHeB" M="3.9899" logL="2.8795" logR="1.6318" logT="3.6673" Mc="0.6777" Menv="3.3122E+00" Spin="5.7134E+00" Z="?"/>
  <TrackPoint Age="175.0728" Stage="CHeB" M="3.9895" logL="2.8609" logR="1.6192" logT="3.6689" Mc="0.6810" Menv="3.3085E+00" Spin="6.0782E+00" Z="?"/>
  <TrackPoint Age="175.3629" Stage="CHeB" M="3.9890" logL="2.8440" logR="1.6078" logT="3.6704" Mc="0.6843" Menv="3.3048E+00" Spin="6.4312E+00" Z="?"/>
  <TrackPoint Age="175.6530" Stage="CHeB" M="3.9886" logL="2.8287" logR="1.5975" logT="3.6717" Mc="0.6875" Menv="3.3011E+00" Spin="6.7694E+00" Z="?"/>
  <TrackPoint Age="175.9430" Stage="CHeB" M="3.9882" logL="2.8149" logR="1.5883" logT="3.6729" Mc="0.6908" Menv="3.2974E+00" Spin="7.0900E+00" Z="?"/>
  <TrackPoint Age="176.2330" Stage="CHeB" M="3.9879" logL="2.8026" logR="1.5800" logT="3.6739" Mc="0.6941" Menv="3.2938E+00" Spin="7.3907E+00" Z="?"/>
  <TrackPoint Age="176.5231" Stage="CHeB" M="3.9875" logL="2.7917" logR="1.5727" logT="3.6749" Mc="0.6974" Menv="3.2901E+00" Spin="7.6695E+00" Z="?"/>
  <TrackPoint Age="176.8132" Stage="CHeB" M="3.9872" logL="2.7821" logR="1.5663" logT="3.6757" Mc="0.7006" Menv="3.2865E+00" Spin="7.9251E+00" Z="?"/>
  <TrackPoint Age="177.1032" Stage="CHeB" M="3.9868" logL="2.7737" logR="1.5606" logT="3.6764" Mc="0.7039" Menv="3.2829E+00" Spin="8.1564E+00" Z="?"/>
  <TrackPoint Age="177.3932" Stage="CHeB" M="3.9865" logL="2.7665" logR="1.5558" logT="3.6770" Mc="0.7072" Menv="3.2793E+00" Spin="8.3629E+00" Z="?"/>
  <TrackPoint Age="177.6833" Stage="CHeB" M="3.9862" logL="2.7603" logR="1.5516" logT="3.6775" Mc="0.7105" Menv="3.2757E+00" Spin="8.5448E+00" Z="?"/>
  <TrackPoint Age="177.9734" Stage="CHeB" M="3.9859" logL="2.7550" logR="1.5481" logT="3.6780" Mc="0.7138" Menv="3.2722E+00" Spin="8.7025E+00" Z="?"/>
  <TrackPoint Age="178.2634" Stage="CHeB" M="3.9856" logL="2.7507" logR="1.5452" logT="3.6783" Mc="0.7170" Menv="3.2686E+00" Spin="8.8369E+00" Z="?"/>
  <TrackPoint Age="178.5535" Stage="CHeB" M="3.9853" logL="2.7471" logR="1.5428" logT="3.6786" Mc="0.7203" Menv="3.2650E+00" Spin="8.9491E+00" Z="?"/>
  <TrackPoint Age="178.8435" Stage="CHeB" M="3.9851" logL="2.7443" logR="1.5409" logT="3.6789" Mc="0.7236" Menv="3.2615E+00" Spin="9.0408E+00" Z="?"/>
  <TrackPoint Age="179.1336" Stage="CHeB" M="3.9848" logL="2.7421" logR="1.5395" logT="3.6790" Mc="0.7269" Menv="3.2579E+00" Spin="9.1138E+00" Z="?"/>
  <TrackPoint Age="179.4236" Stage="CHeB" M="3.9845" logL="2.7405" logR="1.5384" logT="3.6792" Mc="0.7301" Menv="3.2544E+00" Spin="9.1701E+00" Z="?"/>
  <TrackPoint Age="179.7137" Stage="CHeB" M="3.9842" logL="2.7393" logR="1.5376" logT="3.6793" Mc="0.7334" Menv="3.2508E+00" Spin="9.2120E+00" Z="?"/>
  <TrackPoint Age="180.0037" Stage="CHeB" M="3.9840" logL="2.7385" logR="1.5371" logT="3.6793" Mc="0.7367" Menv="3.2473E+00" Spin="9.2417E+00" Z="?"/>
  <TrackPoint Age="180.2938" Stage="CHeB" M="3.9837" logL="2.7381" logR="1.5369" logT="3.6794" Mc="0.7400" Menv="3.2437E+00" Spin="9.2618E+00" Z="?"/>
  <TrackPoint Age="180.5838" Stage="CHeB" M="3.9834" logL="2.7379" logR="1.5367" logT="3.6794" Mc="0.7432" Menv="3.2402E+00" Spin="9.2747E+00" Z="?"/>
  <TrackPoint Age="180.8739" Stage="CHeB" M="3.9831" logL="2.7378" logR="1.5367" logT="3.6794" Mc="0.7465" Menv="3.2366E+00" Spin="9.2830E+00" Z="?"/>
  <TrackPoint Age="181.1639" Stage="CHeB" M="3.9829" logL="2.7390" logR="1.5361" logT="3.6800" Mc="0.7498" Menv="3.1058E+00" Spin="9.5056E+00" Z="?"/>
  <TrackPoint Age="181.4540" Stage="CHeB" M="3.9826" logL="2.7443" logR="1.5335" logT="3.6826" Mc="0.7531" Menv="2.5456E+00" Spin="1.0638E+01" Z="?"/>
  <TrackPoint Age="181.7440" Stage="CHeB" M="3.9823" logL="2.7495" logR="1.5311" logT="3.6851" Mc="0.7563" Menv="2.0915E+00" Spin="1.1857E+01" Z="?"/>
  <TrackPoint Age="182.0341" Stage="CHeB" M="3.9820" logL="2.7545" logR="1.5289" logT="3.6874" Mc="0.7596" Menv="1.7226E+00" Spin="1.3160E+01" Z="?"/>
  <TrackPoint Age="182.3241" Stage="CHeB" M="3.9817" logL="2.7594" logR="1.5270" logT="3.6896" Mc="0.7629" Menv="1.4223E+00" Spin="1.4546E+01" Z="?"/>
  <TrackPoint Age="182.6142" Stage="CHeB" M="3.9815" logL="2.7643" logR="1.5253" logT="3.6917" Mc="0.7662" Menv="1.1770E+00" Spin="1.6010E+01" Z="?"/>
  <TrackPoint Age="182.9042" Stage="CHeB" M="3.9812" logL="2.7692" logR="1.5238" logT="3.6937" Mc="0.7694" Menv="9.7631E-01" Spin="1.7549E+01" Z="?"/>
  <TrackPoint Age="183.1943" Stage="CHeB" M="3.9809" logL="2.7740" logR="1.5224" logT="3.6956" Mc="0.7727" Menv="8.1159E-01" Spin="1.9157E+01" Z="?"/>
  <TrackPoint Age="183.4843" Stage="CHeB" M="3.9806" logL="2.7788" logR="1.5212" logT="3.6973" Mc="0.7760" Menv="6.7605E-01" Spin="2.0829E+01" Z="?"/>
  <TrackPoint Age="183.7744" Stage="CHeB" M="3.9803" logL="2.7836" logR="1.5202" logT="3.6990" Mc="0.7793" Menv="5.6420E-01" Spin="2.2557E+01" Z="?"/>
  <TrackPoint Age="184.0644" Stage="CHeB" M="3.9800" logL="2.7883" logR="1.5194" logT="3.7007" Mc="0.7825" Menv="4.7165E-01" Spin="2.4335E+01" Z="?"/>
  <TrackPoint Age="184.3545" Stage="CHeB" M="3.9797" logL="2.7930" logR="1.5187" logT="3.7022" Mc="0.7858" Menv="3.9485E-01" Spin="2.6156E+01" Z="?"/>
  <TrackPoint Age="184.6445" Stage="CHeB" M="3.9794" logL="2.7978" logR="1.5181" logT="3.7037" Mc="0.7891" Menv="3.3094E-01" Spin="2.8013E+01" Z="?"/>
  <TrackPoint Age="184.9346" Stage="CHeB" M="3.9791" logL="2.8024" logR="1.5176" logT="3.7051" Mc="0.7924" Menv="2.7761E-01" Spin="2.9898E+01" Z="?"/>
  <TrackPoint Age="185.2246" Stage="CHeB" M="3.9788" logL="2.8071" logR="1.5172" logT="3.7064" Mc="0.7956" Menv="2.3298E-01" Spin="3.1807E+01" Z="?"/>
  <TrackPoint Age="185.5147" Stage="CHeB" M="3.9785" logL="2.8118" logR="1.5169" logT="3.7077" Mc="0.7989" Menv="1.9552E-01" Spin="3.3733E+01" Z="?"/>
  <TrackPoint Age="185.8047" Stage="CHeB" M="3.9782" logL="2.8164" logR="1.5167" logT="3.7090" Mc="0.8022" Menv="1.6402E-01" Spin="3.5671E+01" Z="?"/>
  <TrackPoint Age="186.0948" Stage="CHeB" M="3.9779" logL="2.8211" logR="1.5166" logT="3.7103" Mc="0.8055" Menv="1.3745E-01" Spin="3.7617E+01" Z="?"/>
  <TrackPoint Age="186.3849" Stage="CHeB" M="3.9776" logL="2.8257" logR="1.5165" logT="3.7115" Mc="0.8087" Menv="1.1499E-01" Spin="3.9568E+01" Z="?"/>
  <TrackPoint Age="186.6749" Stage="CHeB" M="3.9772" logL="2.8303" logR="1.5164" logT="3.7126" Mc="0.8120" Menv="9.5977E-02" Spin="4.1520E+01" Z="?"/>
  <TrackPoint Age="186.9650" Stage="CHeB" M="3.9769" logL="2.8349" logR="1.5164" logT="3.7138" Mc="0.8153" Menv="7.9854E-02" Spin="4.3471E+01" Z="?"/>
  <TrackPoint Age="187.2550" Stage="CHeB" M="3.9766" logL="2.8395" logR="1.5163" logT="3.7150" Mc="0.8186" Menv="6.6170E-02" Spin="4.5420E+01" Z="?"/>
  <TrackPoint Age="187.5451" Stage="CHeB" M="3.9763" logL="2.8441" logR="1.5163" logT="3.7161" Mc="0.8218" Menv="5.4565E-02" Spin="4.7361E+01" Z="?"/>
  <TrackPoint Age="187.8351" Stage="CHeB" M="3.9759" logL="2.8486" logR="1.5163" logT="3.7173" Mc="0.8251" Menv="4.4783E-02" Spin="4.9277E+01" Z="?"/>
  <TrackPoint Age="188.1252" Stage="CHeB" M="3.9756" logL="2.8532" logR="1.5163" logT="3.7184" Mc="0.8284" Menv="3.6599E-02" Spin="5.1143E+01" Z="?"/>
  <TrackPoint Age="188.4152" Stage="CHeB" M="3.9753" logL="2.8577" logR="1.5164" logT="3.7195" Mc="0.8317" Menv="2.9804E-02" Spin="5.2936E+01" Z="?"/>
  <TrackPoint Age="188.7053" Stage="CHeB" M="3.9749" logL="2.8623" logR="1.5165" logT="3.7206" Mc="0.8349" Menv="2.4200E-02" Spin="5.4635E+01" Z="?"/>
  <TrackPoint Age="188.9953" Stage="CHeB" M="3.9746" logL="2.8668" logR="1.5166" logT="3.7217" Mc="0.8382" Menv="1.9609E-02" Spin="5.6217E+01" Z="?"/>
  <TrackPoint Age="189.2854" Stage="CHeB" M="3.9742" logL="2.8713" logR="1.5169" logT="3.7227" Mc="0.8415" Menv="1.5873E-02" Spin="5.7666E+01" Z="?"/>
  <TrackPoint Age="189.5754" Stage="CHeB" M="3.9738" logL="2.8759" logR="1.5172" logT="3.7236" Mc="0.8448" Menv="1.2850E-02" Spin="5.8966E+01" Z="?"/>
  <TrackPoint Age="189.8655" Stage="CHeB" M="3.9735" logL="2.8804" logR="1.5176" logT="3.7246" Mc="0.8480" Menv="1.0418E-02" Spin="6.0106E+01" Z="?"/>
  <TrackPoint Age="190.1555" Stage="CHeB" M="3.9731" logL="2.8849" logR="1.5181" logT="3.7254" Mc="0.8513" Menv="8.4725E-03" Spin="6.1076E+01" Z="?"/>
  <TrackPoint Age="190.4456" Stage="CHeB" M="3.9728" logL="2.8894" logR="1.5188" logT="3.7262" Mc="0.8546" Menv="6.9234E-03" Spin="6.1872E+01" Z="?"/>
  <TrackPoint Age="190.7356" Stage="CHeB" M="3.9724" logL="2.8939" logR="1.5196" logT="3.7269" Mc="0.8579" Menv="5.6965E-03" Spin="6.2491E+01" Z="?"/>
  <TrackPoint Age="191.0257" Stage="CHeB" M="3.9720" logL="2.8984" logR="1.5206" logT="3.7276" Mc="0.8612" Menv="4.7298E-03" Spin="6.2933E+01" Z="?"/>
  <TrackPoint Age="191.3157" Stage="CHeB" M="3.9716" logL="2.9028" logR="1.5217" logT="3.7281" Mc="0.8644" Menv="3.9728E-03" Spin="6.3201E+01" Z="?"/>
  <TrackPoint Age="191.6058" Stage="CHeB" M="3.9712" logL="2.9073" logR="1.5230" logT="3.7286" Mc="0.8677" Menv="3.3849E-03" Spin="6.3297E+01" Z="?"/>
  <TrackPoint Age="191.8958" Stage="CHeB" M="3.9708" logL="2.9118" logR="1.5245" logT="3.7290" Mc="0.8710" Menv="2.9335E-03" Spin="6.3226E+01" Z="?"/>
  <TrackPoint Age="192.1859" Stage="CHeB" M="3.9704" logL="2.9162" logR="1.5262" logT="3.7292" Mc="0.8743" Menv="2.5935E-03" Spin="6.2992E+01" Z="?"/>
  <TrackPoint Age="192.4759" Stage="CHeB" M="3.9700" logL="2.9207" logR="1.5281" logT="3.7294" Mc="0.8775" Menv="2.3459E-03" Spin="6.2600E+01" Z="?"/>
  <TrackPoint Age="192.7660" Stage="CHeB" M="3.9696" logL="2.9251" logR="1.5302" logT="3.7294" Mc="0.8808" Menv="2.1770E-03" Spin="6.2052E+01" Z="?"/>
  <TrackPoint Age="193.0560" Stage="CHeB" M="3.9692" logL="2.9296" logR="1.5326" logT="3.7294" Mc="0.8841" Menv="2.0780E-03" Spin="6.1353E+01" Z="?"/>
  <TrackPoint Age="193.3461" Stage="CHeB" M="3.9688" logL="2.9340" logR="1.5353" logT="3.7291" Mc="0.8874" Menv="2.0446E-03" Spin="6.0504E+01" Z="?"/>
  <TrackPoint Age="193.6361" Stage="CHeB" M="3.9684" logL="2.9384" logR="1.5382" logT="3.7288" Mc="0.8906" Menv="2.0773E-03" Spin="5.9504E+01" Z="?"/>
  <TrackPoint Age="193.9262" Stage="CHeB" M="3.9679" logL="2.9429" logR="1.5414" logT="3.7283" Mc="0.8939" Menv="2.1819E-03" Spin="5.8352E+01" Z="?"/>
  <TrackPoint Age="194.2162" Stage="CHeB" M="3.9675" logL="2.9473" logR="1.5449" logT="3.7277" Mc="0.8972" Menv="2.3702E-03" Spin="5.7045E+01" Z="?"/>
  <TrackPoint Age="194.5063" Stage="CHeB" M="3.9670" logL="2.9517" logR="1.5487" logT="3.7269" Mc="0.9005" Menv="2.6627E-03" Spin="5.5578E+01" Z="?"/>
  <TrackPoint Age="194.7963" Stage="CHeB" M="3.9666" logL="2.9561" logR="1.5528" logT="3.7259" Mc="0.9037" Menv="3.0907E-03" Spin="5.3945E+01" Z="?"/>
  <TrackPoint Age="195.0864" Stage="CHeB" M="3.9661" logL="2.9605" logR="1.5572" logT="3.7248" Mc="0.9070" Menv="3.7013E-03" Spin="5.2138E+01" Z="?"/>
  <TrackPoint Age="195.3764" Stage="CHeB" M="3.9656" logL="2.9649" logR="1.5621" logT="3.7235" Mc="0.9103" Menv="4.5644E-03" Spin="5.0147E+01" Z="?"/>
  <TrackPoint Age="195.6665" Stage="CHeB" M="3.9651" logL="2.9693" logR="1.5672" logT="3.7220" Mc="0.9136" Menv="5.7828E-03" Spin="4.7965E+01" Z="?"/>
  <TrackPoint Age="195.9565" Stage="CHeB" M="3.9646" logL="2.9737" logR="1.5728" logT="3.7203" Mc="0.9168" Menv="7.5071E-03" Spin="4.5584E+01" Z="?"/>
  <TrackPoint Age="196.2466" Stage="CHeB" M="3.9641" logL="2.9781" logR="1.5788" logT="3.7184" Mc="0.9201" Menv="9.9588E-03" Spin="4.3002E+01" Z="?"/>
  <TrackPoint Age="196.5367" Stage="CHeB" M="3.9636" logL="2.9825" logR="1.5851" logT="3.7163" Mc="0.9234" Menv="1.3463E-02" Spin="4.0221E+01" Z="?"/>
  <TrackPoint Age="196.8267" Stage="CHeB" M="3.9630" logL="2.9869" logR="1.5919" logT="3.7140" Mc="0.9267" Menv="1.8496E-02" Spin="3.7254E+01" Z="?"/>
  <TrackPoint Age="197.1167" Stage="CHeB" M="3.9625" logL="2.9912" logR="1.5991" logT="3.7115" Mc="0.9299" Menv="2.5758E-02" Spin="3.4128E+01" Z="?"/>
  <TrackPoint Age="197.4068" Stage="CHeB" M="3.9619" logL="2.9956" logR="1.6068" logT="3.7088" Mc="0.9332" Menv="3.6274E-02" Spin="3.0880E+01" Z="?"/>
  <TrackPoint Age="197.6969" Stage="CHeB" M="3.9613" logL="3.0000" logR="1.6149" logT="3.7058" Mc="0.9365" Menv="5.1548E-02" Spin="2.7565E+01" Z="?"/>
  <TrackPoint Age="197.9869" Stage="CHeB" M="3.9607" logL="3.0043" logR="1.6235" logT="3.7026" Mc="0.9398" Menv="7.3772E-02" Spin="2.4251E+01" Z="?"/>
  <TrackPoint Age="198.2770" Stage="CHeB" M="3.9601" logL="3.0087" logR="1.6326" logT="3.6991" Mc="0.9430" Menv="1.0615E-01" Spin="2.1013E+01" Z="?"/>
  <TrackPoint Age="198.5670" Stage="CHeB" M="3.9594" logL="3.0130" logR="1.6422" logT="3.6954" Mc="0.9463" Menv="1.5332E-01" Spin="1.7925E+01" Z="?"/>
  <TrackPoint Age="198.8571" Stage="CHeB" M="3.9588" logL="3.0174" logR="1.6523" logT="3.6914" Mc="0.9496" Menv="2.2205E-01" Spin="1.5055E+01" Z="?"/>
  <TrackPoint Age="199.1471" Stage="CHeB" M="3.9581" logL="3.0217" logR="1.6630" logT="3.6872" Mc="0.9529" Menv="3.2209E-01" Spin="1.2455E+01" Z="?"/>
  <TrackPoint Age="199.4372" Stage="CHeB" M="3.9574" logL="3.0260" logR="1.6742" logT="3.6827" Mc="0.9561" Menv="4.6752E-01" Spin="1.0157E+01" Z="?"/>
  <TrackPoint Age="199.7272" Stage="CHeB" M="3.9566" logL="3.0304" logR="1.6860" logT="3.6779" Mc="0.9594" Menv="6.7859E-01" Spin="8.1751E+00" Z="?"/>
  <TrackPoint Age="200.0173" Stage="CHeB" M="3.9559" logL="3.0347" logR="1.6984" logT="3.6728" Mc="0.9627" Menv="9.8434E-01" Spin="6.5011E+00" Z="?"/>
  <TrackPoint Age="200.3073" Stage="CHeB" M="3.9551" logL="3.0390" logR="1.7113" logT="3.6673" Mc="0.9660" Menv="1.4263E+00" Spin="5.1149E+00" Z="?"/>
  <TrackPoint Age="200.5974" Stage="CHeB" M="3.9543" logL="3.0433" logR="1.7249" logT="3.6616" Mc="0.9692" Menv="2.0637E+00" Spin="3.9863E+00" Z="?"/>
  <TrackPoint Age="200.8874" Stage="FAGB" M="3.9534" logL="3.0476" logR="1.7392" logT="3.6556" Mc="0.9725" Menv="2.9809E+00" Spin="3.0812E+00" Z="?"/>
  <TrackPoint Age="200.9164" Stage="FAGB" M="3.9533" logL="3.0586" logR="1.7466" logT="3.6546" Mc="0.9725" Menv="2.9808E+00" Spin="2.9754E+00" Z="?"/>
  <TrackPoint Age="200.9449" Stage="FAGB" M="3.9532" logL="3.0696" logR="1.7540" logT="3.6537" Mc="0.9725" Menv="2.9807E+00" Spin="2.8734E+00" Z="?"/>
  <TrackPoint Age="200.9727" Stage="FAGB" M="3.9531" logL="3.0805" logR="1.7614" logT="3.6527" Mc="0.9725" Menv="2.9806E+00" Spin="2.7750E+00" Z="?"/>
  <TrackPoint Age="201.0000" Stage="FAGB" M="3.9530" logL="3.0915" logR="1.7688" logT="3.6518" Mc="0.9725" Menv="2.9805E+00" Spin="2.6801E+00" Z="?"/>
  <TrackPoint Age="201.0268" Stage="FAGB" M="3.9529" logL="3.1025" logR="1.7762" logT="3.6508" Mc="0.9725" Menv="2.9804E+00" Spin="2.5885E+00" Z="?"/>
  <TrackPoint Age="201.0530" Stage="FAGB" M="3.9528" logL="3.1134" logR="1.7836" logT="3.6498" Mc="0.9725" Menv="2.9803E+00" Spin="2.5002E+00" Z="?"/>
  <TrackPoint Age="201.0787" Stage="FAGB" M="3.9527" logL="3.1244" logR="1.7910" logT="3.6488" Mc="0.9725" Menv="2.9802E+00" Spin="2.4150E+00" Z="?"/>
  <TrackPoint Age="201.1039" Stage="FAGB" M="3.9526" logL="3.1354" logR="1.7985" logT="3.6479" Mc="0.9725" Menv="2.9801E+00" Spin="2.3327E+00" Z="?"/>
  <TrackPoint Age="201.1286" Stage="FAGB" M="3.9525" logL="3.1463" logR="1.8059" logT="3.6469" Mc="0.9725" Menv="2.9800E+00" Spin="2.2533E+00" Z="?"/>
  <TrackPoint Age="201.1527" Stage="FAGB" M="3.9524" logL="3.1573" logR="1.8134" logT="3.6459" Mc="0.9725" Menv="2.9799E+00" Spin="2.1767E+00" Z="?"/>
  <TrackPoint Age="201.1765" Stage="FAGB" M="3.9523" logL="3.1683" logR="1.8208" logT="3.6449" Mc="0.9725" Menv="2.9798E+00" Spin="2.1028E+00" Z="?"/>
  <TrackPoint Age="201.1997" Stage="FAGB" M="3.9522" logL="3.1792" logR="1.8282" logT="3.6440" Mc="0.9725" Menv="2.9797E+00" Spin="2.0314E+00" Z="?"/>
  <TrackPoint Age="201.2224" Stage="FAGB" M="3.9521" logL="3.1902" logR="1.8357" logT="3.6430" Mc="0.9725" Menv="2.9795E+00" Spin="1.9625E+00" Z="?"/>
  <TrackPoint Age="201.2448" Stage="FAGB" M="3.9519" logL="3.2012" logR="1.8432" logT="3.6420" Mc="0.9725" Menv="2.9794E+00" Spin="1.8961E+00" Z="?"/>
  <TrackPoint Age="201.2666" Stage="FAGB" M="3.9518" logL="3.2121" logR="1.8506" logT="3.6410" Mc="0.9725" Menv="2.9793E+00" Spin="1.8319E+00" Z="?"/>
  <TrackPoint Age="201.2880" Stage="FAGB" M="3.9517" logL="3.2231" logR="1.8581" logT="3.6400" Mc="0.9725" Menv="2.9792E+00" Spin="1.7699E+00" Z="?"/>
  <TrackPoint Age="201.3090" Stage="FAGB" M="3.9516" logL="3.2341" logR="1.8655" logT="3.6390" Mc="0.9725" Menv="2.9791E+00" Spin="1.7101E+00" Z="?"/>
  <TrackPoint Age="201.3296" Stage="FAGB" M="3.9514" logL="3.2450" logR="1.8730" logT="3.6380" Mc="0.9725" Menv="2.9789E+00" Spin="1.6523E+00" Z="?"/>
  <TrackPoint Age="201.3498" Stage="FAGB" M="3.9513" logL="3.2560" logR="1.8805" logT="3.6370" Mc="0.9725" Menv="2.9788E+00" Spin="1.5965E+00" Z="?"/>
  <TrackPoint Age="201.3695" Stage="FAGB" M="3.9512" logL="3.2670" logR="1.8880" logT="3.6360" Mc="0.9725" Menv="2.9787E+00" Spin="1.5426E+00" Z="?"/>
  <TrackPoint Age="201.3889" Stage="FAGB" M="3.9510" logL="3.2780" logR="1.8955" logT="3.6350" Mc="0.9725" Menv="2.9785E+00" Spin="1.4906E+00" Z="?"/>
  <TrackPoint Age="201.4079" Stage="FAGB" M="3.9509" logL="3.2889" logR="1.9030" logT="3.6340" Mc="0.9725" Menv="2.9784E+00" Spin="1.4403E+00" Z="?"/>
  <TrackPoint Age="201.4265" Stage="FAGB" M="3.9507" logL="3.2999" logR="1.9104" logT="3.6330" Mc="0.9725" Menv="2.9782E+00" Spin="1.3918E+00" Z="?"/>
  <TrackPoint Age="201.4447" Stage="FAGB" M="3.9506" logL="3.3109" logR="1.9179" logT="3.6320" Mc="0.9725" Menv="2.9781E+00" Spin="1.3449E+00" Z="?"/>
  <TrackPoint Age="201.4626" Stage="FAGB" M="3.9504" logL="3.3218" logR="1.9254" logT="3.6310" Mc="0.9725" Menv="2.9779E+00" Spin="1.2997E+00" Z="?"/>
  <TrackPoint Age="201.4801" Stage="FAGB" M="3.9503" logL="3.3328" logR="1.9329" logT="3.6300" Mc="0.9725" Menv="2.9778E+00" Spin="1.2559E+00" Z="?"/>
  <TrackPoint Age="201.4972" Stage="FAGB" M="3.9501" logL="3.3438" logR="1.9405" logT="3.6290" Mc="0.9725" Menv="2.9776E+00" Spin="1.2137E+00" Z="?"/>
  <TrackPoint Age="201.5141" Stage="FAGB" M="3.9500" logL="3.3547" logR="1.9480" logT="3.6280" Mc="0.9725" Menv="2.9774E+00" Spin="1.1729E+00" Z="?"/>
  <TrackPoint Age="201.5305" Stage="FAGB" M="3.9498" logL="3.3657" logR="1.9555" logT="3.6270" Mc="0.9725" Menv="2.9773E+00" Spin="1.1334E+00" Z="?"/>
  <TrackPoint Age="201.5467" Stage="FAGB" M="3.9496" logL="3.3767" logR="1.9630" logT="3.6259" Mc="0.9725" Menv="2.9771E+00" Spin="1.0953E+00" Z="?"/>
  <TrackPoint Age="201.5625" Stage="FAGB" M="3.9494" logL="3.3876" logR="1.9705" logT="3.6249" Mc="0.9725" Menv="2.9769E+00" Spin="1.0585E+00" Z="?"/>
  <TrackPoint Age="201.5780" Stage="FAGB" M="3.9493" logL="3.3986" logR="1.9781" logT="3.6239" Mc="0.9725" Menv="2.9767E+00" Spin="1.0229E+00" Z="?"/>
  <TrackPoint Age="201.5932" Stage="FAGB" M="3.9491" logL="3.4096" logR="1.9856" logT="3.6229" Mc="0.9725" Menv="2.9766E+00" Spin="9.8855E-01" Z="?"/>
  <TrackPoint Age="201.6081" Stage="FAGB" M="3.9489" logL="3.4205" logR="1.9931" logT="3.6218" Mc="0.9725" Menv="2.9764E+00" Spin="9.5533E-01" Z="?"/>
  <TrackPoint Age="201.6227" Stage="FAGB" M="3.9487" logL="3.4315" logR="2.0007" logT="3.6208" Mc="0.9725" Menv="2.9762E+00" Spin="9.2323E-01" Z="?"/>
  <TrackPoint Age="201.6370" Stage="FAGB" M="3.9485" logL="3.4425" logR="2.0082" logT="3.6198" Mc="0.9725" Menv="2.9760E+00" Spin="8.9221E-01" Z="?"/>
  <TrackPoint Age="201.6510" Stage="FAGB" M="3.9483" logL="3.4534" logR="2.0158" logT="3.6188" Mc="0.9725" Menv="2.9758E+00" Spin="8.6223E-01" Z="?"/>
  <TrackPoint Age="201.6647" Stage="FAGB" M="3.9481" logL="3.4644" logR="2.0233" logT="3.6177" Mc="0.9725" Menv="2.9756E+00" Spin="8.3324E-01" Z="?"/>
  <TrackPoint Age="201.6782" Stage="FAGB" M="3.9479" logL="3.4754" logR="2.0309" logT="3.6167" Mc="0.9725" Menv="2.9754E+00" Spin="8.0523E-01" Z="?"/>
  <TrackPoint Age="201.6914" Stage="FAGB" M="3.9477" logL="3.4863" logR="2.0384" logT="3.6156" Mc="0.9725" Menv="2.9752E+00" Spin="7.7816E-01" Z="?"/>
  <TrackPoint Age="201.7043" Stage="FAGB" M="3.9475" logL="3.4973" logR="2.0460" logT="3.6146" Mc="0.9725" Menv="2.9749E+00" Spin="7.5198E-01" Z="?"/>
  <TrackPoint Age="201.7170" Stage="FAGB" M="3.9472" logL="3.5083" logR="2.0535" logT="3.6136" Mc="0.9725" Menv="2.9747E+00" Spin="7.2668E-01" Z="?"/>
  <TrackPoint Age="201.7294" Stage="FAGB" M="3.9470" logL="3.5192" logR="2.0611" logT="3.6125" Mc="0.9725" Menv="2.9745E+00" Spin="7.0222E-01" Z="?"/>
  <TrackPoint Age="201.7416" Stage="FAGB" M="3.9468" logL="3.5302" logR="2.0687" logT="3.6115" Mc="0.9725" Menv="2.9743E+00" Spin="6.7858E-01" Z="?"/>
  <TrackPoint Age="201.7535" Stage="FAGB" M="3.9465" logL="3.5412" logR="2.0763" logT="3.6104" Mc="0.9725" Menv="2.9740E+00" Spin="6.5571E-01" Z="?"/>
  <TrackPoint Age="201.7652" Stage="FAGB" M="3.9463" logL="3.5521" logR="2.0838" logT="3.6094" Mc="0.9725" Menv="2.9738E+00" Spin="6.3361E-01" Z="?"/>
  <TrackPoint Age="201.7767" Stage="FAGB" M="3.9460" logL="3.5631" logR="2.0914" logT="3.6083" Mc="0.9725" Menv="2.9735E+00" Spin="6.1224E-01" Z="?"/>
  <TrackPoint Age="201.7879" Stage="FAGB" M="3.9458" logL="3.5741" logR="2.0990" logT="3.6073" Mc="0.9725" Menv="2.9733E+00" Spin="5.9157E-01" Z="?"/>
  <TrackPoint Age="201.7989" Stage="FAGB" M="3.9455" logL="3.5850" logR="2.1066" logT="3.6062" Mc="0.9725" Menv="2.9730E+00" Spin="5.7159E-01" Z="?"/>
  <TrackPoint Age="201.8097" Stage="FAGB" M="3.9452" logL="3.5960" logR="2.1142" logT="3.6052" Mc="0.9725" Menv="2.9727E+00" Spin="5.5227E-01" Z="?"/>
  <TrackPoint Age="201.8202" Stage="FAGB" M="3.9450" logL="3.6070" logR="2.1218" logT="3.6041" Mc="0.9725" Menv="2.9725E+00" Spin="5.3358E-01" Z="?"/>
  <TrackPoint Age="201.8306" Stage="FAGB" M="3.9447" logL="3.6179" logR="2.1294" logT="3.6031" Mc="0.9725" Menv="2.9722E+00" Spin="5.1551E-01" Z="?"/>
  <TrackPoint Age="201.8407" Stage="FAGB" M="3.9444" logL="3.6289" logR="2.1370" logT="3.6020" Mc="0.9725" Menv="2.9719E+00" Spin="4.9803E-01" Z="?"/>
  <TrackPoint Age="201.8507" Stage="FAGB" M="3.9441" logL="3.6399" logR="2.1446" logT="3.6009" Mc="0.9725" Menv="2.9716E+00" Spin="4.8113E-01" Z="?"/>
  <TrackPoint Age="201.8604" Stage="FAGB" M="3.9438" logL="3.6508" logR="2.1522" logT="3.5999" Mc="0.9725" Menv="2.9713E+00" Spin="4.6478E-01" Z="?"/>
  <TrackPoint Age="201.8700" Stage="FAGB" M="3.9435" logL="3.6618" logR="2.1598" logT="3.5988" Mc="0.9725" Menv="2.9710E+00" Spin="4.4897E-01" Z="?"/>
  <TrackPoint Age="201.8793" Stage="FAGB" M="3.9432" logL="3.6728" logR="2.1674" logT="3.5978" Mc="0.9725" Menv="2.9707E+00" Spin="4.3367E-01" Z="?"/>
  <TrackPoint Age="201.8885" Stage="FAGB" M="3.9429" logL="3.6837" logR="2.1750" logT="3.5967" Mc="0.9725" Menv="2.9703E+00" Spin="4.1887E-01" Z="?"/>
  <TrackPoint Age="201.8975" Stage="FAGB" M="3.9425" logL="3.6947" logR="2.1827" logT="3.5956" Mc="0.9725" Menv="2.9700E+00" Spin="4.0456E-01" Z="?"/>
  <TrackPoint Age="201.9063" Stage="FAGB" M="3.9422" logL="3.7057" logR="2.1903" logT="3.5945" Mc="0.9725" Menv="2.9697E+00" Spin="3.9071E-01" Z="?"/>
  <TrackPoint Age="201.9149" Stage="FAGB" M="3.9419" logL="3.7166" logR="2.1979" logT="3.5935" Mc="0.9725" Menv="2.9693E+00" Spin="3.7731E-01" Z="?"/>
  <TrackPoint Age="201.9234" Stage="FAGB" M="3.9415" logL="3.7276" logR="2.2055" logT="3.5924" Mc="0.9725" Menv="2.9690E+00" Spin="3.6435E-01" Z="?"/>
  <TrackPoint Age="201.9317" Stage="FAGB" M="3.9411" logL="3.7386" logR="2.2132" logT="3.5913" Mc="0.9725" Menv="2.9686E+00" Spin="3.5180E-01" Z="?"/>
  <TrackPoint Age="201.9398" Stage="FAGB" M="3.9408" logL="3.7496" logR="2.2208" logT="3.5902" Mc="0.9725" Menv="2.9683E+00" Spin="3.3966E-01" Z="?"/>
  <TrackPoint Age="201.9478" Stage="FAGB" M="3.9404" logL="3.7605" logR="2.2285" logT="3.5892" Mc="0.9725" Menv="2.9679E+00" Spin="3.2791E-01" Z="?"/>
  <TrackPoint Age="201.9556" Stage="FAGB" M="3.9400" logL="3.7715" logR="2.2361" logT="3.5881" Mc="0.9725" Menv="2.9675E+00" Spin="3.1653E-01" Z="?"/>
  <TrackPoint Age="201.9632" Stage="FAGB" M="3.9396" logL="3.7825" logR="2.2438" logT="3.5870" Mc="0.9725" Menv="2.9671E+00" Spin="3.0552E-01" Z="?"/>
  <TrackPoint Age="201.9707" Stage="FAGB" M="3.9392" logL="3.7934" logR="2.2514" logT="3.5859" Mc="0.9725" Menv="2.9667E+00" Spin="2.9487E-01" Z="?"/>
  <TrackPoint Age="201.9780" Stage="FAGB" M="3.9388" logL="3.8044" logR="2.2591" logT="3.5848" Mc="0.9725" Menv="2.9663E+00" Spin="2.8455E-01" Z="?"/>
  <TrackPoint Age="201.9852" Stage="FAGB" M="3.9384" logL="3.8154" logR="2.2667" logT="3.5838" Mc="0.9725" Menv="2.9659E+00" Spin="2.7456E-01" Z="?"/>
  <TrackPoint Age="201.9923" Stage="FAGB" M="3.9379" logL="3.8263" logR="2.2744" logT="3.5827" Mc="0.9725" Menv="2.9654E+00" Spin="2.6488E-01" Z="?"/>
  <TrackPoint Age="201.9992" Stage="FAGB" M="3.9375" logL="3.8373" logR="2.2820" logT="3.5816" Mc="0.9725" Menv="2.9650E+00" Spin="2.5550E-01" Z="?"/>
  <TrackPoint Age="202.0060" Stage="FAGB" M="3.9370" logL="3.8483" logR="2.2897" logT="3.5805" Mc="0.9725" Menv="2.9645E+00" Spin="2.4641E-01" Z="?"/>
  <TrackPoint Age="202.0126" Stage="FAGB" M="3.9366" logL="3.8592" logR="2.2974" logT="3.5794" Mc="0.9725" Menv="2.9641E+00" Spin="2.3758E-01" Z="?"/>
  <TrackPoint Age="202.0191" Stage="FAGB" M="3.9361" logL="3.8702" logR="2.3050" logT="3.5783" Mc="0.9725" Menv="2.9636E+00" Spin="2.2901E-01" Z="?"/>
  <TrackPoint Age="202.0255" Stage="FAGB" M="3.9356" logL="3.8812" logR="2.3127" logT="3.5772" Mc="0.9725" Menv="2.9631E+00" Spin="2.2068E-01" Z="?"/>
  <TrackPoint Age="202.0317" Stage="FAGB" M="3.9351" logL="3.8921" logR="2.3204" logT="3.5761" Mc="0.9725" Menv="2.9626E+00" Spin="2.1255E-01" Z="?"/>
  <TrackPoint Age="202.0379" Stage="FAGB" M="3.9346" logL="3.9031" logR="2.3281" logT="3.5750" Mc="0.9725" Menv="2.9621E+00" Spin="2.0461E-01" Z="?"/>
  <TrackPoint Age="202.0439" Stage="FAGB" M="3.9341" logL="3.9141" logR="2.3358" logT="3.5739" Mc="0.9725" Menv="2.9616E+00" Spin="1.9682E-01" Z="?"/>
  <TrackPoint Age="202.0497" Stage="FAGB" M="3.9336" logL="3.9250" logR="2.3435" logT="3.5728" Mc="0.9725" Menv="2.9610E+00" Spin="1.8913E-01" Z="?"/>
  <TrackPoint Age="202.0555" Stage="FAGB" M="3.9330" logL="3.9360" logR="2.3511" logT="3.5717" Mc="0.9725" Menv="2.9605E+00" Spin="1.8147E-01" Z="?"/>
  <TrackPoint Age="202.0612" Stage="FAGB" M="3.9325" logL="3.9470" logR="2.3588" logT="3.5706" Mc="0.9725" Menv="2.9599E+00" Spin="1.7377E-01" Z="?"/>
  <TrackPoint Age="202.0667" Stage="FAGB" M="3.9319" logL="3.9579" logR="2.3665" logT="3.5695" Mc="0.9725" Menv="2.9594E+00" Spin="1.6591E-01" Z="?"/>
  <TrackPoint Age="202.0721" Stage="FAGB" M="3.9313" logL="3.9689" logR="2.3742" logT="3.5684" Mc="0.9725" Menv="2.9588E+00" Spin="1.5772E-01" Z="?"/>
  <TrackPoint Age="202.0774" Stage="FAGB" M="3.9307" logL="3.9799" logR="2.3819" logT="3.5673" Mc="0.9725" Menv="2.9582E+00" Spin="1.4898E-01" Z="?"/>
  <TrackPoint Age="202.0826" Stage="FAGB" M="3.9301" logL="3.9908" logR="2.3896" logT="3.5662" Mc="0.9725" Menv="2.9576E+00" Spin="1.4184E-01" Z="?"/>
  <TrackPoint Age="202.0877" Stage="FAGB" M="3.9295" logL="4.0018" logR="2.3973" logT="3.5650" Mc="0.9725" Menv="2.9570E+00" Spin="1.3652E-01" Z="?"/>
  <TrackPoint Age="202.0927" Stage="FAGB" M="3.9288" logL="4.0128" logR="2.4051" logT="3.5639" Mc="0.9725" Menv="2.9563E+00" Spin="1.3138E-01" Z="?"/>
  <TrackPoint Age="202.0976" Stage="FAGB" M="3.9282" logL="4.0237" logR="2.4128" logT="3.5628" Mc="0.9725" Menv="2.9557E+00" Spin="1.2640E-01" Z="?"/>
  <TrackPoint Age="202.1024" Stage="FAGB" M="3.9275" logL="4.0347" logR="2.4205" logT="3.5617" Mc="0.9725" Menv="2.9550E+00" Spin="1.2158E-01" Z="?"/>
  <TrackPoint Age="202.1072" Stage="FAGB" M="3.9268" logL="4.0457" logR="2.4282" logT="3.5606" Mc="0.9725" Menv="2.9543E+00" Spin="1.1692E-01" Z="?"/>
  <TrackPoint Age="202.1118" Stage="FAGB" M="3.9261" logL="4.0566" logR="2.4359" logT="3.5595" Mc="0.9725" Menv="2.9536E+00" Spin="1.1241E-01" Z="?"/>
  <TrackPoint Age="202.1163" Stage="FAGB" M="3.9254" logL="4.0676" logR="2.4437" logT="3.5583" Mc="0.9725" Menv="2.9529E+00" Spin="1.0805E-01" Z="?"/>
  <TrackPoint Age="202.1207" Stage="FAGB" M="3.9247" logL="4.0786" logR="2.4514" logT="3.5572" Mc="0.9725" Menv="2.9522E+00" Spin="1.0384E-01" Z="?"/>
  <TrackPoint Age="202.1251" Stage="FAGB" M="3.9239" logL="4.0895" logR="2.4591" logT="3.5561" Mc="0.9725" Menv="2.9514E+00" Spin="9.9761E-02" Z="?"/>
  <TrackPoint Age="202.1293" Stage="FAGB" M="3.9232" logL="4.1005" logR="2.4668" logT="3.5550" Mc="0.9725" Menv="2.9507E+00" Spin="9.5818E-02" Z="?"/>
  <TrackPoint Age="202.1335" Stage="FAGB" M="3.9224" logL="4.1115" logR="2.4746" logT="3.5538" Mc="0.9725" Menv="2.9499E+00" Spin="9.2006E-02" Z="?"/>
  <TrackPoint Age="202.1376" Stage="FAGB" M="3.9216" logL="4.1224" logR="2.4823" logT="3.5527" Mc="0.9725" Menv="2.9491E+00" Spin="8.8320E-02" Z="?"/>
  <TrackPoint Age="202.1416" Stage="FAGB" M="3.9208" logL="4.1334" logR="2.4901" logT="3.5516" Mc="0.9725" Menv="2.9482E+00" Spin="8.4759E-02" Z="?"/>
  <TrackPoint Age="202.1455" Stage="FAGB" M="3.9199" logL="4.1444" logR="2.4978" logT="3.5505" Mc="0.9725" Menv="2.9474E+00" Spin="8.1316E-02" Z="?"/>
  <TrackPoint Age="202.1494" Stage="FAGB" M="3.9191" logL="4.1553" logR="2.5056" logT="3.5493" Mc="0.9725" Menv="2.9465E+00" Spin="7.7991E-02" Z="?"/>
  <TrackPoint Age="202.1531" Stage="FAGB" M="3.9182" logL="4.1663" logR="2.5133" logT="3.5482" Mc="0.9725" Menv="2.9457E+00" Spin="7.4778E-02" Z="?"/>
  <TrackPoint Age="202.1568" Stage="FAGB" M="3.9173" logL="4.1773" logR="2.5211" logT="3.5471" Mc="0.9725" Menv="2.9448E+00" Spin="7.1676E-02" Z="?"/>
  <TrackPoint Age="202.1604" Stage="FAGB" M="3.9164" logL="4.1882" logR="2.5288" logT="3.5459" Mc="0.9725" Menv="2.9438E+00" Spin="6.8680E-02" Z="?"/>
  <TrackPoint Age="202.1605" Stage="SAGB" M="3.9163" logL="4.1885" logR="2.5290" logT="3.5459" Mc="0.8759" Menv="3.0404E+00" Spin="7.1351E-02" Z="?"/>
  <TrackPoint Age="202.1655" Stage="SAGB" M="3.9150" logL="4.1909" logR="2.5307" logT="3.5456" Mc="0.8760" Menv="3.0390E+00" Spin="7.0573E-02" Z="?"/>
  <TrackPoint Age="202.1705" Stage="SAGB" M="3.9137" logL="4.1934" logR="2.5325" logT="3.5454" Mc="0.8761" Menv="3.0376E+00" Spin="6.9798E-02" Z="?"/>
  <TrackPoint Age="202.1755" Stage="SAGB" M="3.9123" logL="4.1958" logR="2.5343" logT="3.5451" Mc="0.8762" Menv="3.0361E+00" Spin="6.9026E-02" Z="?"/>
  <TrackPoint Age="202.1805" Stage="SAGB" M="3.9109" logL="4.1983" logR="2.5361" logT="3.5448" Mc="0.8763" Menv="3.0346E+00" Spin="6.8258E-02" Z="?"/>
  <TrackPoint Age="202.1855" Stage="SAGB" M="3.9095" logL="4.2008" logR="2.5379" logT="3.5445" Mc="0.8764" Menv="3.0331E+00" Spin="6.7493E-02" Z="?"/>
  <TrackPoint Age="202.1905" Stage="SAGB" M="3.9081" logL="4.2033" logR="2.5397" logT="3.5442" Mc="0.8765" Menv="3.0316E+00" Spin="6.6731E-02" Z="?"/>
  <TrackPoint Age="202.1955" Stage="SAGB" M="3.9067" logL="4.2058" logR="2.5415" logT="3.5440" Mc="0.8766" Menv="3.0301E+00" Spin="6.5973E-02" Z="?"/>
  <TrackPoint Age="202.2005" Stage="SAGB" M="3.9053" logL="4.2083" logR="2.5433" logT="3.5437" Mc="0.8767" Menv="3.0286E+00" Spin="6.5218E-02" Z="?"/>
  <TrackPoint Age="202.2055" Stage="SAGB" M="3.9038" logL="4.2108" logR="2.5452" logT="3.5434" Mc="0.8768" Menv="3.0270E+00" Spin="6.4466E-02" Z="?"/>
  <TrackPoint Age="202.2105" Stage="SAGB" M="3.9024" logL="4.2133" logR="2.5470" logT="3.5431" Mc="0.8769" Menv="3.0255E+00" Spin="6.3718E-02" Z="?"/>
  <TrackPoint Age="202.2155" Stage="SAGB" M="3.9009" logL="4.2159" logR="2.5489" logT="3.5428" Mc="0.8770" Menv="3.0239E+00" Spin="6.2974E-02" Z="?"/>
  <TrackPoint Age="202.2205" Stage="SAGB" M="3.8994" logL="4.2184" logR="2.5507" logT="3.5425" Mc="0.8771" Menv="3.0223E+00" Spin="6.2233E-02" Z="?"/>
  <TrackPoint Age="202.2255" Stage="SAGB" M="3.8979" logL="4.2210" logR="2.5526" logT="3.5422" Mc="0.8772" Menv="3.0207E+00" Spin="6.1495E-02" Z="?"/>
  <TrackPoint Age="202.2305" Stage="SAGB" M="3.8964" logL="4.2236" logR="2.5545" logT="3.5419" Mc="0.8773" Menv="3.0191E+00" Spin="6.0761E-02" Z="?"/>
  <TrackPoint Age="202.2355" Stage="SAGB" M="3.8948" logL="4.2262" logR="2.5564" logT="3.5416" Mc="0.8774" Menv="3.0174E+00" Spin="6.0031E-02" Z="?"/>
  <TrackPoint Age="202.2405" Stage="SAGB" M="3.8933" logL="4.2288" logR="2.5583" logT="3.5413" Mc="0.8776" Menv="3.0157E+00" Spin="5.9304E-02" Z="?"/>
  <TrackPoint Age="202.2455" Stage="SAGB" M="3.8917" logL="4.2314" logR="2.5602" logT="3.5410" Mc="0.8777" Menv="3.0141E+00" Spin="5.8581E-02" Z="?"/>
  <TrackPoint Age="202.2505" Stage="SAGB" M="3.8901" logL="4.2341" logR="2.5621" logT="3.5407" Mc="0.8778" Menv="3.0124E+00" Spin="5.7861E-02" Z="?"/>
  <TrackPoint Age="202.2555" Stage="SAGB" M="3.8885" logL="4.2367" logR="2.5640" logT="3.5404" Mc="0.8779" Menv="3.0106E+00" Spin="5.7145E-02" Z="?"/>
  <TrackPoint Age="202.2605" Stage="SAGB" M="3.8869" logL="4.2394" logR="2.5660" logT="3.5401" Mc="0.8780" Menv="3.0089E+00" Spin="5.6433E-02" Z="?"/>
  <TrackPoint Age="202.2655" Stage="SAGB" M="3.8853" logL="4.2421" logR="2.5679" logT="3.5398" Mc="0.8781" Menv="3.0072E+00" Spin="5.5724E-02" Z="?"/>
  <TrackPoint Age="202.2705" Stage="SAGB" M="3.8836" logL="4.2447" logR="2.5699" logT="3.5395" Mc="0.8782" Menv="3.0054E+00" Spin="5.5019E-02" Z="?"/>
  <TrackPoint Age="202.2755" Stage="SAGB" M="3.8819" logL="4.2474" logR="2.5718" logT="3.5392" Mc="0.8783" Menv="3.0036E+00" Spin="5.4318E-02" Z="?"/>
  <TrackPoint Age="202.2805" Stage="SAGB" M="3.8802" logL="4.2502" logR="2.5738" logT="3.5389" Mc="0.8784" Menv="3.0018E+00" Spin="5.3621E-02" Z="?"/>
  <TrackPoint Age="202.2855" Stage="SAGB" M="3.8785" logL="4.2529" logR="2.5758" logT="3.5386" Mc="0.8785" Menv="2.9999E+00" Spin="5.2927E-02" Z="?"/>
  <TrackPoint Age="202.2905" Stage="SAGB" M="3.8768" logL="4.2556" logR="2.5778" logT="3.5383" Mc="0.8787" Menv="2.9981E+00" Spin="5.2237E-02" Z="?"/>
  <TrackPoint Age="202.2955" Stage="SAGB" M="3.8750" logL="4.2584" logR="2.5798" logT="3.5380" Mc="0.8788" Menv="2.9962E+00" Spin="5.1551E-02" Z="?"/>
  <TrackPoint Age="202.3005" Stage="SAGB" M="3.8732" logL="4.2612" logR="2.5818" logT="3.5376" Mc="0.8789" Menv="2.9943E+00" Spin="5.0869E-02" Z="?"/>
  <TrackPoint Age="202.3055" Stage="SAGB" M="3.8714" logL="4.2639" logR="2.5839" logT="3.5373" Mc="0.8790" Menv="2.9924E+00" Spin="5.0190E-02" Z="?"/>
  <TrackPoint Age="202.3105" Stage="SAGB" M="3.8696" logL="4.2667" logR="2.5859" logT="3.5370" Mc="0.8791" Menv="2.9905E+00" Spin="4.9516E-02" Z="?"/>
  <TrackPoint Age="202.3155" Stage="SAGB" M="3.8678" logL="4.2696" logR="2.5880" logT="3.5367" Mc="0.8792" Menv="2.9885E+00" Spin="4.8845E-02" Z="?"/>
  <TrackPoint Age="202.3205" Stage="SAGB" M="3.8659" logL="4.2724" logR="2.5900" logT="3.5364" Mc="0.8794" Menv="2.9865E+00" Spin="4.8179E-02" Z="?"/>
  <TrackPoint Age="202.3255" Stage="SAGB" M="3.8640" logL="4.2752" logR="2.5921" logT="3.5360" Mc="0.8795" Menv="2.9845E+00" Spin="4.7516E-02" Z="?"/>
  <TrackPoint Age="202.3305" Stage="SAGB" M="3.8621" logL="4.2781" logR="2.5942" logT="3.5357" Mc="0.8796" Menv="2.9825E+00" Spin="4.6858E-02" Z="?"/>
  <TrackPoint Age="202.3355" Stage="SAGB" M="3.8602" logL="4.2810" logR="2.5963" logT="3.5354" Mc="0.8797" Menv="2.9805E+00" Spin="4.6203E-02" Z="?"/>
  <TrackPoint Age="202.3405" Stage="SAGB" M="3.8582" logL="4.2839" logR="2.5984" logT="3.5350" Mc="0.8798" Menv="2.9784E+00" Spin="4.5553E-02" Z="?"/>
  <TrackPoint Age="202.3455" Stage="SAGB" M="3.8562" logL="4.2868" logR="2.6005" logT="3.5347" Mc="0.8800" Menv="2.9763E+00" Spin="4.4906E-02" Z="?"/>
  <TrackPoint Age="202.3505" Stage="SAGB" M="3.8542" logL="4.2897" logR="2.6027" logT="3.5344" Mc="0.8801" Menv="2.9742E+00" Spin="4.4264E-02" Z="?"/>
  <TrackPoint Age="202.3555" Stage="SAGB" M="3.8522" logL="4.2926" logR="2.6048" logT="3.5340" Mc="0.8802" Menv="2.9720E+00" Spin="4.3626E-02" Z="?"/>
  <TrackPoint Age="202.3605" Stage="SAGB" M="3.8502" logL="4.2956" logR="2.6070" logT="3.5337" Mc="0.8803" Menv="2.9698E+00" Spin="4.2991E-02" Z="?"/>
  <TrackPoint Age="202.3655" Stage="SAGB" M="3.8481" logL="4.2985" logR="2.6092" logT="3.5333" Mc="0.8805" Menv="2.9676E+00" Spin="4.2362E-02" Z="?"/>
  <TrackPoint Age="202.3705" Stage="SAGB" M="3.8460" logL="4.3015" logR="2.6113" logT="3.5330" Mc="0.8806" Menv="2.9654E+00" Spin="4.1736E-02" Z="?"/>
  <TrackPoint Age="202.3755" Stage="SAGB" M="3.8439" logL="4.3045" logR="2.6135" logT="3.5326" Mc="0.8807" Menv="2.9632E+00" Spin="4.1114E-02" Z="?"/>
  <TrackPoint Age="202.3805" Stage="SAGB" M="3.8417" logL="4.3075" logR="2.6158" logT="3.5323" Mc="0.8808" Menv="2.9609E+00" Spin="4.0497E-02" Z="?"/>
  <TrackPoint Age="202.3855" Stage="SAGB" M="3.8395" logL="4.3106" logR="2.6180" logT="3.5319" Mc="0.8810" Menv="2.9586E+00" Spin="3.9884E-02" Z="?"/>
  <TrackPoint Age="202.3905" Stage="SAGB" M="3.8373" logL="4.3136" logR="2.6202" logT="3.5316" Mc="0.8811" Menv="2.9562E+00" Spin="3.9276E-02" Z="?"/>
  <TrackPoint Age="202.3955" Stage="SAGB" M="3.8351" logL="4.3167" logR="2.6225" logT="3.5312" Mc="0.8812" Menv="2.9539E+00" Spin="3.8671E-02" Z="?"/>
  <TrackPoint Age="202.4005" Stage="SAGB" M="3.8328" logL="4.3198" logR="2.6247" logT="3.5308" Mc="0.8814" Menv="2.9515E+00" Spin="3.8071E-02" Z="?"/>
  <TrackPoint Age="202.4055" Stage="SAGB" M="3.8305" logL="4.3229" logR="2.6270" logT="3.5305" Mc="0.8815" Menv="2.9490E+00" Spin="3.7476E-02" Z="?"/>
  <TrackPoint Age="202.4105" Stage="SAGB" M="3.8282" logL="4.3260" logR="2.6293" logT="3.5301" Mc="0.8816" Menv="2.9466E+00" Spin="3.6885E-02" Z="?"/>
  <TrackPoint Age="202.4155" Stage="SAGB" M="3.8258" logL="4.3291" logR="2.6316" logT="3.5297" Mc="0.8818" Menv="2.9441E+00" Spin="3.6298E-02" Z="?"/>
  <TrackPoint Age="202.4205" Stage="SAGB" M="3.8235" logL="4.3323" logR="2.6339" logT="3.5294" Mc="0.8819" Menv="2.9415E+00" Spin="3.5716E-02" Z="?"/>
  <TrackPoint Age="202.4255" Stage="SAGB" M="3.8210" logL="4.3355" logR="2.6363" logT="3.5290" Mc="0.8820" Menv="2.9390E+00" Spin="3.5138E-02" Z="?"/>
  <TrackPoint Age="202.4305" Stage="SAGB" M="3.8186" logL="4.3387" logR="2.6386" logT="3.5286" Mc="0.8822" Menv="2.9364E+00" Spin="3.4565E-02" Z="?"/>
  <TrackPoint Age="202.4355" Stage="SAGB" M="3.8161" logL="4.3419" logR="2.6410" logT="3.5282" Mc="0.8823" Menv="2.9338E+00" Spin="3.3996E-02" Z="?"/>
  <TrackPoint Age="202.4405" Stage="SAGB" M="3.8136" logL="4.3451" logR="2.6434" logT="3.5279" Mc="0.8825" Menv="2.9311E+00" Spin="3.3432E-02" Z="?"/>
  <TrackPoint Age="202.4455" Stage="SAGB" M="3.8110" logL="4.3484" logR="2.6458" logT="3.5275" Mc="0.8826" Menv="2.9284E+00" Spin="3.2872E-02" Z="?"/>
  <TrackPoint Age="202.4505" Stage="SAGB" M="3.8084" logL="4.3516" logR="2.6482" logT="3.5271" Mc="0.8827" Menv="2.9257E+00" Spin="3.2317E-02" Z="?"/>
  <TrackPoint Age="202.4555" Stage="SAGB" M="3.8058" logL="4.3549" logR="2.6506" logT="3.5267" Mc="0.8829" Menv="2.9229E+00" Spin="3.1767E-02" Z="?"/>
  <TrackPoint Age="202.4605" Stage="SAGB" M="3.8031" logL="4.3582" logR="2.6531" logT="3.5263" Mc="0.8830" Menv="2.9201E+00" Spin="3.1222E-02" Z="?"/>
  <TrackPoint Age="202.4655" Stage="SAGB" M="3.8004" logL="4.3616" logR="2.6555" logT="3.5259" Mc="0.8832" Menv="2.9173E+00" Spin="3.0681E-02" Z="?"/>
  <TrackPoint Age="202.4705" Stage="SAGB" M="3.7977" logL="4.3649" logR="2.6580" logT="3.5255" Mc="0.8833" Menv="2.9144E+00" Spin="3.0145E-02" Z="?"/>
  <TrackPoint Age="202.4755" Stage="SAGB" M="3.7949" logL="4.3683" logR="2.6605" logT="3.5251" Mc="0.8835" Menv="2.9115E+00" Spin="2.9613E-02" Z="?"/>
  <TrackPoint Age="202.4805" Stage="SAGB" M="3.7921" logL="4.3717" logR="2.6630" logT="3.5247" Mc="0.8836" Menv="2.9085E+00" Spin="2.9087E-02" Z="?"/>
  <TrackPoint Age="202.4855" Stage="SAGB" M="3.7893" logL="4.3751" logR="2.6655" logT="3.5243" Mc="0.8838" Menv="2.9055E+00" Spin="2.8565E-02" Z="?"/>
  <TrackPoint Age="202.4905" Stage="SAGB" M="3.7864" logL="4.3785" logR="2.6681" logT="3.5239" Mc="0.8839" Menv="2.9024E+00" Spin="2.8048E-02" Z="?"/>
  <TrackPoint Age="202.4955" Stage="SAGB" M="3.7834" logL="4.3820" logR="2.6706" logT="3.5235" Mc="0.8841" Menv="2.8994E+00" Spin="2.7536E-02" Z="?"/>
  <TrackPoint Age="202.5005" Stage="SAGB" M="3.7804" logL="4.3855" logR="2.6732" logT="3.5230" Mc="0.8842" Menv="2.8962E+00" Spin="2.7028E-02" Z="?"/>
  <TrackPoint Age="202.5055" Stage="SAGB" M="3.7774" logL="4.3890" logR="2.6758" logT="3.5226" Mc="0.8844" Menv="2.8930E+00" Spin="2.6526E-02" Z="?"/>
  <TrackPoint Age="202.5105" Stage="SAGB" M="3.7743" logL="4.3925" logR="2.6784" logT="3.5222" Mc="0.8845" Menv="2.8898E+00" Spin="2.6029E-02" Z="?"/>
  <TrackPoint Age="202.5155" Stage="SAGB" M="3.7712" logL="4.3961" logR="2.6811" logT="3.5218" Mc="0.8847" Menv="2.8865E+00" Spin="2.5536E-02" Z="?"/>
  <TrackPoint Age="202.5205" Stage="SAGB" M="3.7681" logL="4.3996" logR="2.6837" logT="3.5213" Mc="0.8849" Menv="2.8832E+00" Spin="2.5048E-02" Z="?"/>
  <TrackPoint Age="202.5255" Stage="SAGB" M="3.7648" logL="4.4032" logR="2.6864" logT="3.5209" Mc="0.8850" Menv="2.8798E+00" Spin="2.4566E-02" Z="?"/>
  <TrackPoint Age="202.5305" Stage="SAGB" M="3.7616" logL="4.4068" logR="2.6891" logT="3.5205" Mc="0.8852" Menv="2.8764E+00" Spin="2.4088E-02" Z="?"/>
  <TrackPoint Age="202.5355" Stage="SAGB" M="3.7583" logL="4.4105" logR="2.6918" logT="3.5200" Mc="0.8853" Menv="2.8729E+00" Spin="2.3616E-02" Z="?"/>
  <TrackPoint Age="202.5405" Stage="SAGB" M="3.7549" logL="4.4142" logR="2.6945" logT="3.5196" Mc="0.8855" Menv="2.8694E+00" Spin="2.3148E-02" Z="?"/>
  <TrackPoint Age="202.5455" Stage="SAGB" M="3.7515" logL="4.4179" logR="2.6972" logT="3.5191" Mc="0.8857" Menv="2.8658E+00" Spin="2.2686E-02" Z="?"/>
  <TrackPoint Age="202.5505" Stage="SAGB" M="3.7480" logL="4.4216" logR="2.7000" logT="3.5187" Mc="0.8858" Menv="2.8622E+00" Spin="2.2228E-02" Z="?"/>
  <TrackPoint Age="202.5555" Stage="SAGB" M="3.7445" logL="4.4253" logR="2.7028" logT="3.5182" Mc="0.8860" Menv="2.8585E+00" Spin="2.1776E-02" Z="?"/>
  <TrackPoint Age="202.5605" Stage="SAGB" M="3.7409" logL="4.4291" logR="2.7056" logT="3.5177" Mc="0.8862" Menv="2.8547E+00" Spin="2.1329E-02" Z="?"/>
  <TrackPoint Age="202.5655" Stage="SAGB" M="3.7372" logL="4.4329" logR="2.7085" logT="3.5173" Mc="0.8863" Menv="2.8509E+00" Spin="2.0887E-02" Z="?"/>
  <TrackPoint Age="202.5705" Stage="SAGB" M="3.7335" logL="4.4367" logR="2.7113" logT="3.5168" Mc="0.8865" Menv="2.8470E+00" Spin="2.0450E-02" Z="?"/>
  <TrackPoint Age="202.5755" Stage="SAGB" M="3.7298" logL="4.4406" logR="2.7142" logT="3.5163" Mc="0.8867" Menv="2.8431E+00" Spin="2.0018E-02" Z="?"/>
  <TrackPoint Age="202.5805" Stage="SAGB" M="3.7259" logL="4.4444" logR="2.7171" logT="3.5158" Mc="0.8869" Menv="2.8391E+00" Spin="1.9592E-02" Z="?"/>
  <TrackPoint Age="202.5855" Stage="SAGB" M="3.7220" logL="4.4484" logR="2.7200" logT="3.5154" Mc="0.8870" Menv="2.8350E+00" Spin="1.9170E-02" Z="?"/>
  <TrackPoint Age="202.5905" Stage="SAGB" M="3.7181" logL="4.4523" logR="2.7229" logT="3.5149" Mc="0.8872" Menv="2.8309E+00" Spin="1.8754E-02" Z="?"/>
  <TrackPoint Age="202.5955" Stage="SAGB" M="3.7141" logL="4.4563" logR="2.7259" logT="3.5144" Mc="0.8874" Menv="2.8267E+00" Spin="1.8343E-02" Z="?"/>
  <TrackPoint Age="202.6005" Stage="SAGB" M="3.7100" logL="4.4603" logR="2.7289" logT="3.5139" Mc="0.8876" Menv="2.8224E+00" Spin="1.7938E-02" Z="?"/>
  <TrackPoint Age="202.6055" Stage="SAGB" M="3.7058" logL="4.4643" logR="2.7319" logT="3.5134" Mc="0.8878" Menv="2.8180E+00" Spin="1.7537E-02" Z="?"/>
  <TrackPoint Age="202.6105" Stage="SAGB" M="3.7016" logL="4.4683" logR="2.7350" logT="3.5129" Mc="0.8880" Menv="2.8136E+00" Spin="1.7142E-02" Z="?"/>
  <TrackPoint Age="202.6155" Stage="SAGB" M="3.6972" logL="4.4724" logR="2.7380" logT="3.5124" Mc="0.8881" Menv="2.8091E+00" Spin="1.6752E-02" Z="?"/>
  <TrackPoint Age="202.6205" Stage="SAGB" M="3.6928" logL="4.4765" logR="2.7411" logT="3.5118" Mc="0.8883" Menv="2.8045E+00" Spin="1.6367E-02" Z="?"/>
  <TrackPoint Age="202.6255" Stage="SAGB" M="3.6884" logL="4.4807" logR="2.7442" logT="3.5113" Mc="0.8885" Menv="2.7999E+00" Spin="1.5988E-02" Z="?"/>
  <TrackPoint Age="202.6305" Stage="SAGB" M="3.6829" logL="4.4849" logR="2.7474" logT="3.5108" Mc="0.8887" Menv="2.7942E+00" Spin="1.5598E-02" Z="?"/>
  <TrackPoint Age="202.6355" Stage="SAGB" M="3.6757" logL="4.4891" logR="2.7507" logT="3.5102" Mc="0.8889" Menv="2.7868E+00" Spin="1.5189E-02" Z="?"/>
  <TrackPoint Age="202.6405" Stage="SAGB" M="3.6661" logL="4.4933" logR="2.7541" logT="3.5096" Mc="0.8891" Menv="2.7770E+00" Spin="1.4751E-02" Z="?"/>
  <TrackPoint Age="202.6455" Stage="SAGB" M="3.6529" logL="4.4976" logR="2.7576" logT="3.5088" Mc="0.8893" Menv="2.7636E+00" Spin="1.4270E-02" Z="?"/>
  <TrackPoint Age="202.6505" Stage="SAGB" M="3.6340" logL="4.5019" logR="2.7614" logT="3.5080" Mc="0.8895" Menv="2.7445E+00" Spin="1.3720E-02" Z="?"/>
  <TrackPoint Age="202.6555" Stage="SAGB" M="3.6050" logL="4.5062" logR="2.7657" logT="3.5070" Mc="0.8897" Menv="2.7153E+00" Spin="1.3048E-02" Z="?"/>
  <TrackPoint Age="202.6591" Stage="SAGB" M="3.5689" logL="4.5094" logR="2.7694" logT="3.5059" Mc="0.8899" Menv="2.6791E+00" Spin="1.2382E-02" Z="?"/>
  <TrackPoint Age="202.6611" Stage="SAGB" M="3.5333" logL="4.5111" logR="2.7721" logT="3.5050" Mc="0.8899" Menv="2.6433E+00" Spin="1.1826E-02" Z="?"/>
  <TrackPoint Age="202.6623" Stage="SAGB" M="3.4979" logL="4.5122" logR="2.7744" logT="3.5041" Mc="0.8900" Menv="2.6079E+00" Spin="1.1333E-02" Z="?"/>
  <TrackPoint Age="202.6631" Stage="SAGB" M="3.4629" logL="4.5129" logR="2.7763" logT="3.5033" Mc="0.8900" Menv="2.5729E+00" Spin="1.0880E-02" Z="?"/>
  <TrackPoint Age="202.6639" Stage="SAGB" M="3.4283" logL="4.5136" logR="2.7783" logT="3.5025" Mc="0.8901" Menv="2.5383E+00" Spin="1.0446E-02" Z="?"/>
  <TrackPoint Age="202.6647" Stage="SAGB" M="3.3940" logL="4.5143" logR="2.7803" logT="3.5017" Mc="0.8901" Menv="2.5039E+00" Spin="1.0030E-02" Z="?"/>
  <TrackPoint Age="202.6654" Stage="SAGB" M="3.3601" logL="4.5150" logR="2.7822" logT="3.5009" Mc="0.8901" Menv="2.4700E+00" Spin="9.6319E-03" Z="?"/>
  <TrackPoint Age="202.6662" Stage="SAGB" M="3.3265" logL="4.5156" logR="2.7842" logT="3.5001" Mc="0.8902" Menv="2.4363E+00" Spin="9.2508E-03" Z="?"/>
  <TrackPoint Age="202.6669" Stage="SAGB" M="3.2932" logL="4.5163" logR="2.7861" logT="3.4993" Mc="0.8902" Menv="2.4030E+00" Spin="8.8858E-03" Z="?"/>
  <TrackPoint Age="202.6677" Stage="SAGB" M="3.2603" logL="4.5169" logR="2.7881" logT="3.4985" Mc="0.8902" Menv="2.3701E+00" Spin="8.5363E-03" Z="?"/>
  <TrackPoint Age="202.6684" Stage="SAGB" M="3.2277" logL="4.5176" logR="2.7900" logT="3.4977" Mc="0.8902" Menv="2.3374E+00" Spin="8.2014E-03" Z="?"/>
  <TrackPoint Age="202.6691" Stage="SAGB" M="3.1954" logL="4.5182" logR="2.7919" logT="3.4969" Mc="0.8903" Menv="2.3051E+00" Spin="7.8807E-03" Z="?"/>
  <TrackPoint Age="202.6698" Stage="SAGB" M="3.1635" logL="4.5189" logR="2.7939" logT="3.4961" Mc="0.8903" Menv="2.2732E+00" Spin="7.5734E-03" Z="?"/>
  <TrackPoint Age="202.6705" Stage="SAGB" M="3.1318" logL="4.5195" logR="2.7958" logT="3.4953" Mc="0.8903" Menv="2.2415E+00" Spin="7.2791E-03" Z="?"/>
  <TrackPoint Age="202.6712" Stage="SAGB" M="3.1005" logL="4.5201" logR="2.7977" logT="3.4945" Mc="0.8904" Menv="2.2101E+00" Spin="6.9970E-03" Z="?"/>
  <TrackPoint Age="202.6719" Stage="SAGB" M="3.0695" logL="4.5207" logR="2.7996" logT="3.4936" Mc="0.8904" Menv="2.1791E+00" Spin="6.7268E-03" Z="?"/>
  <TrackPoint Age="202.6726" Stage="SAGB" M="3.0388" logL="4.5214" logR="2.8015" logT="3.4928" Mc="0.8904" Menv="2.1484E+00" Spin="6.4677E-03" Z="?"/>
  <TrackPoint Age="202.6733" Stage="SAGB" M="3.0084" logL="4.5220" logR="2.8034" logT="3.4920" Mc="0.8904" Menv="2.1180E+00" Spin="6.2195E-03" Z="?"/>
  <TrackPoint Age="202.6740" Stage="SAGB" M="2.9783" logL="4.5226" logR="2.8053" logT="3.4912" Mc="0.8905" Menv="2.0879E+00" Spin="5.9816E-03" Z="?"/>
  <TrackPoint Age="202.6746" Stage="SAGB" M="2.9485" logL="4.5231" logR="2.8072" logT="3.4904" Mc="0.8905" Menv="2.0580E+00" Spin="5.7535E-03" Z="?"/>
  <TrackPoint Age="202.6753" Stage="SAGB" M="2.9191" logL="4.5237" logR="2.8091" logT="3.4896" Mc="0.8905" Menv="2.0285E+00" Spin="5.5348E-03" Z="?"/>
  <TrackPoint Age="202.6759" Stage="SAGB" M="2.8899" logL="4.5243" logR="2.8110" logT="3.4888" Mc="0.8906" Menv="1.9993E+00" Spin="5.3251E-03" Z="?"/>
  <TrackPoint Age="202.6765" Stage="SAGB" M="2.8610" logL="4.5249" logR="2.8127" logT="3.4881" Mc="0.8906" Menv="1.9593E+00" Spin="5.1448E-03" Z="?"/>
  <TrackPoint Age="202.6772" Stage="SAGB" M="2.8324" logL="4.5255" logR="2.8144" logT="3.4875" Mc="0.8906" Menv="1.9176E+00" Spin="4.9753E-03" Z="?"/>
  <TrackPoint Age="202.6778" Stage="SAGB" M="2.8040" logL="4.5260" logR="2.8160" logT="3.4868" Mc="0.8906" Menv="1.8764E+00" Spin="4.8115E-03" Z="?"/>
  <TrackPoint Age="202.6784" Stage="SAGB" M="2.7760" logL="4.5266" logR="2.8176" logT="3.4861" Mc="0.8907" Menv="1.8358E+00" Spin="4.6533E-03" Z="?"/>
  <TrackPoint Age="202.6790" Stage="SAGB" M="2.7482" logL="4.5271" logR="2.8193" logT="3.4854" Mc="0.8907" Menv="1.7958E+00" Spin="4.5005E-03" Z="?"/>
  <TrackPoint Age="202.6796" Stage="SAGB" M="2.7208" logL="4.5277" logR="2.8209" logT="3.4847" Mc="0.8907" Menv="1.7564E+00" Spin="4.3529E-03" Z="?"/>
  <TrackPoint Age="202.6802" Stage="SAGB" M="2.6935" logL="4.5282" logR="2.8225" logT="3.4841" Mc="0.8907" Menv="1.7175E+00" Spin="4.2103E-03" Z="?"/>
  <TrackPoint Age="202.6808" Stage="SAGB" M="2.6666" logL="4.5287" logR="2.8241" logT="3.4834" Mc="0.8908" Menv="1.6793E+00" Spin="4.0725E-03" Z="?"/>
  <TrackPoint Age="202.6814" Stage="SAGB" M="2.6399" logL="4.5293" logR="2.8257" logT="3.4827" Mc="0.8908" Menv="1.6416E+00" Spin="3.9394E-03" Z="?"/>
  <TrackPoint Age="202.6819" Stage="SAGB" M="2.6135" logL="4.5298" logR="2.8273" logT="3.4821" Mc="0.8908" Menv="1.6044E+00" Spin="3.8107E-03" Z="?"/>
  <TrackPoint Age="202.6825" Stage="SAGB" M="2.5874" logL="4.5303" logR="2.8289" logT="3.4814" Mc="0.8908" Menv="1.5678E+00" Spin="3.6864E-03" Z="?"/>
  <TrackPoint Age="202.6831" Stage="SAGB" M="2.5615" logL="4.5308" logR="2.8305" logT="3.4807" Mc="0.8909" Menv="1.5317E+00" Spin="3.5663E-03" Z="?"/>
  <TrackPoint Age="202.6836" Stage="SAGB" M="2.5359" logL="4.5313" logR="2.8321" logT="3.4801" Mc="0.8909" Menv="1.4962E+00" Spin="3.4501E-03" Z="?"/>
  <TrackPoint Age="202.6842" Stage="SAGB" M="2.5106" logL="4.5318" logR="2.8336" logT="3.4794" Mc="0.8909" Menv="1.4612E+00" Spin="3.3379E-03" Z="?"/>
  <TrackPoint Age="202.6847" Stage="SAGB" M="2.4855" logL="4.5323" logR="2.8352" logT="3.4788" Mc="0.8909" Menv="1.4267E+00" Spin="3.2293E-03" Z="?"/>
  <TrackPoint Age="202.6853" Stage="SAGB" M="2.4606" logL="4.5328" logR="2.8367" logT="3.4781" Mc="0.8910" Menv="1.3927E+00" Spin="3.1244E-03" Z="?"/>
  <TrackPoint Age="202.6858" Stage="SAGB" M="2.4360" logL="4.5333" logR="2.8383" logT="3.4775" Mc="0.8910" Menv="1.3593E+00" Spin="3.0229E-03" Z="?"/>
  <TrackPoint Age="202.6863" Stage="SAGB" M="2.4116" logL="4.5338" logR="2.8398" logT="3.4768" Mc="0.8910" Menv="1.3264E+00" Spin="2.9248E-03" Z="?"/>
  <TrackPoint Age="202.6868" Stage="SAGB" M="2.3875" logL="4.5343" logR="2.8414" logT="3.4762" Mc="0.8910" Menv="1.2940E+00" Spin="2.8299E-03" Z="?"/>
  <TrackPoint Age="202.6873" Stage="SAGB" M="2.3636" logL="4.5347" logR="2.8429" logT="3.4755" Mc="0.8911" Menv="1.2620E+00" Spin="2.7381E-03" Z="?"/>
  <TrackPoint Age="202.6879" Stage="SAGB" M="2.3400" logL="4.5352" logR="2.8444" logT="3.4749" Mc="0.8911" Menv="1.2306E+00" Spin="2.6492E-03" Z="?"/>
  <TrackPoint Age="202.6884" Stage="SAGB" M="2.3166" logL="4.5357" logR="2.8459" logT="3.4742" Mc="0.8911" Menv="1.1997E+00" Spin="2.5633E-03" Z="?"/>
  <TrackPoint Age="202.6888" Stage="SAGB" M="2.2934" logL="4.5361" logR="2.8474" logT="3.4736" Mc="0.8911" Menv="1.1692E+00" Spin="2.4801E-03" Z="?"/>
  <TrackPoint Age="202.6893" Stage="SAGB" M="2.2705" logL="4.5366" logR="2.8489" logT="3.4730" Mc="0.8911" Menv="1.1393E+00" Spin="2.3996E-03" Z="?"/>
  <TrackPoint Age="202.6898" Stage="SAGB" M="2.2478" logL="4.5370" logR="2.8504" logT="3.4723" Mc="0.8912" Menv="1.1098E+00" Spin="2.3217E-03" Z="?"/>
  <TrackPoint Age="202.6903" Stage="SAGB" M="2.2253" logL="4.5375" logR="2.8519" logT="3.4717" Mc="0.8912" Menv="1.0808E+00" Spin="2.2463E-03" Z="?"/>
  <TrackPoint Age="202.6908" Stage="SAGB" M="2.2031" logL="4.5379" logR="2.8533" logT="3.4711" Mc="0.8912" Menv="1.0523E+00" Spin="2.1732E-03" Z="?"/>
  <TrackPoint Age="202.6912" Stage="SAGB" M="2.1810" logL="4.5383" logR="2.8548" logT="3.4704" Mc="0.8912" Menv="1.0242E+00" Spin="2.1025E-03" Z="?"/>
  <TrackPoint Age="202.6917" Stage="SAGB" M="2.1592" logL="4.5388" logR="2.8563" logT="3.4698" Mc="0.8912" Menv="9.9657E-01" Spin="2.0340E-03" Z="?"/>
  <TrackPoint Age="202.6922" Stage="SAGB" M="2.1376" logL="4.5392" logR="2.8577" logT="3.4692" Mc="0.8913" Menv="9.6941E-01" Spin="1.9676E-03" Z="?"/>
  <TrackPoint Age="202.6926" Stage="SAGB" M="2.1163" logL="4.5396" logR="2.8592" logT="3.4686" Mc="0.8913" Menv="9.4271E-01" Spin="1.9033E-03" Z="?"/>
  <TrackPoint Age="202.6931" Stage="SAGB" M="2.0951" logL="4.5400" logR="2.8606" logT="3.4680" Mc="0.8913" Menv="9.1645E-01" Spin="1.8410E-03" Z="?"/>
  <TrackPoint Age="202.6935" Stage="SAGB" M="2.0741" logL="4.5404" logR="2.8620" logT="3.4674" Mc="0.8913" Menv="8.9064E-01" Spin="1.7805E-03" Z="?"/>
  <TrackPoint Age="202.6940" Stage="SAGB" M="2.0534" logL="4.5408" logR="2.8634" logT="3.4668" Mc="0.8913" Menv="8.6527E-01" Spin="1.7220E-03" Z="?"/>
  <TrackPoint Age="202.6944" Stage="SAGB" M="2.0329" logL="4.5413" logR="2.8648" logT="3.4662" Mc="0.8914" Menv="8.4033E-01" Spin="1.6652E-03" Z="?"/>
  <TrackPoint Age="202.6948" Stage="SAGB" M="2.0125" logL="4.5417" logR="2.8662" logT="3.4656" Mc="0.8914" Menv="8.1583E-01" Spin="1.6101E-03" Z="?"/>
  <TrackPoint Age="202.6953" Stage="SAGB" M="1.9924" logL="4.5421" logR="2.8676" logT="3.4650" Mc="0.8914" Menv="7.9175E-01" Spin="1.5566E-03" Z="?"/>
  <TrackPoint Age="202.6957" Stage="SAGB" M="1.9725" logL="4.5424" logR="2.8690" logT="3.4644" Mc="0.8914" Menv="7.6811E-01" Spin="1.5048E-03" Z="?"/>
  <TrackPoint Age="202.6961" Stage="SAGB" M="1.9528" logL="4.5428" logR="2.8704" logT="3.4638" Mc="0.8914" Menv="7.4488E-01" Spin="1.4545E-03" Z="?"/>
  <TrackPoint Age="202.6965" Stage="SAGB" M="1.9332" logL="4.5432" logR="2.8717" logT="3.4632" Mc="0.8915" Menv="7.2207E-01" Spin="1.4056E-03" Z="?"/>
  <TrackPoint Age="202.6969" Stage="SAGB" M="1.9139" logL="4.5436" logR="2.8734" logT="3.4625" Mc="0.8915" Menv="6.9968E-01" Spin="1.3563E-03" Z="?"/>
  <TrackPoint Age="202.6973" Stage="SAGB" M="1.8948" logL="4.5440" logR="2.8751" logT="3.4617" Mc="0.8915" Menv="6.7770E-01" Spin="1.3078E-03" Z="?"/>
  <TrackPoint Age="202.6977" Stage="SAGB" M="1.8758" logL="4.5443" logR="2.8768" logT="3.4609" Mc="0.8915" Menv="6.5613E-01" Spin="1.2610E-03" Z="?"/>
  <TrackPoint Age="202.6981" Stage="SAGB" M="1.8571" logL="4.5447" logR="2.8785" logT="3.4602" Mc="0.8915" Menv="6.3496E-01" Spin="1.2156E-03" Z="?"/>
  <TrackPoint Age="202.6985" Stage="SAGB" M="1.8385" logL="4.5451" logR="2.8802" logT="3.4594" Mc="0.8915" Menv="6.1420E-01" Spin="1.1718E-03" Z="?"/>
  <TrackPoint Age="202.6989" Stage="SAGB" M="1.8201" logL="4.5454" logR="2.8818" logT="3.4587" Mc="0.8916" Menv="5.9384E-01" Spin="1.1294E-03" Z="?"/>
  <TrackPoint Age="202.6992" Stage="SAGB" M="1.8019" logL="4.5458" logR="2.8834" logT="3.4580" Mc="0.8916" Menv="5.7387E-01" Spin="1.0883E-03" Z="?"/>
  <TrackPoint Age="202.6996" Stage="SAGB" M="1.7839" logL="4.5462" logR="2.8850" logT="3.4573" Mc="0.8916" Menv="5.5429E-01" Spin="1.0485E-03" Z="?"/>
  <TrackPoint Age="202.7000" Stage="SAGB" M="1.7661" logL="4.5465" logR="2.8865" logT="3.4566" Mc="0.8916" Menv="5.3510E-01" Spin="1.0099E-03" Z="?"/>
  <TrackPoint Age="202.7004" Stage="SAGB" M="1.7484" logL="4.5468" logR="2.8880" logT="3.4560" Mc="0.8916" Menv="5.1630E-01" Spin="9.7251E-04" Z="?"/>
  <TrackPoint Age="202.7007" Stage="SAGB" M="1.7309" logL="4.5472" logR="2.8895" logT="3.4553" Mc="0.8916" Menv="4.9788E-01" Spin="9.3625E-04" Z="?"/>
  <TrackPoint Age="202.7011" Stage="SAGB" M="1.7136" logL="4.5475" logR="2.8907" logT="3.4548" Mc="0.8917" Menv="4.7985E-01" Spin="9.0227E-04" Z="?"/>
  <TrackPoint Age="202.7014" Stage="SAGB" M="1.6965" logL="4.5479" logR="2.8917" logT="3.4544" Mc="0.8917" Menv="4.6219E-01" Spin="8.6951E-04" Z="?"/>
  <TrackPoint Age="202.7018" Stage="SAGB" M="1.6795" logL="4.5482" logR="2.8927" logT="3.4539" Mc="0.8917" Menv="4.4491E-01" Spin="8.3763E-04" Z="?"/>
  <TrackPoint Age="202.7021" Stage="SAGB" M="1.6627" logL="4.5485" logR="2.8937" logT="3.4535" Mc="0.8917" Menv="4.2800E-01" Spin="8.0660E-04" Z="?"/>
  <TrackPoint Age="202.7025" Stage="SAGB" M="1.6461" logL="4.5489" logR="2.8947" logT="3.4531" Mc="0.8917" Menv="4.1146E-01" Spin="7.7639E-04" Z="?"/>
  <TrackPoint Age="202.7028" Stage="SAGB" M="1.6296" logL="4.5492" logR="2.8957" logT="3.4527" Mc="0.8917" Menv="3.9529E-01" Spin="7.4696E-04" Z="?"/>
  <TrackPoint Age="202.7032" Stage="SAGB" M="1.6133" logL="4.5495" logR="2.8966" logT="3.4524" Mc="0.8918" Menv="3.7949E-01" Spin="7.1828E-04" Z="?"/>
  <TrackPoint Age="202.7035" Stage="SAGB" M="1.5972" logL="4.5498" logR="2.8975" logT="3.4520" Mc="0.8918" Menv="3.6404E-01" Spin="6.9031E-04" Z="?"/>
  <TrackPoint Age="202.7038" Stage="SAGB" M="1.5812" logL="4.5501" logR="2.8983" logT="3.4516" Mc="0.8918" Menv="3.4896E-01" Spin="6.6304E-04" Z="?"/>
  <TrackPoint Age="202.7042" Stage="SAGB" M="1.5654" logL="4.5504" logR="2.8991" logT="3.4513" Mc="0.8918" Menv="3.3423E-01" Spin="6.3643E-04" Z="?"/>
  <TrackPoint Age="202.7045" Stage="SAGB" M="1.5497" logL="4.5507" logR="2.8999" logT="3.4510" Mc="0.8918" Menv="3.1986E-01" Spin="6.1046E-04" Z="?"/>
  <TrackPoint Age="202.7048" Stage="SAGB" M="1.5342" logL="4.5510" logR="2.9007" logT="3.4507" Mc="0.8918" Menv="3.0584E-01" Spin="5.8510E-04" Z="?"/>
  <TrackPoint Age="202.7051" Stage="SAGB" M="1.5189" logL="4.5513" logR="2.9014" logT="3.4504" Mc="0.8918" Menv="2.9217E-01" Spin="5.6033E-04" Z="?"/>
  <TrackPoint Age="202.7054" Stage="SAGB" M="1.5037" logL="4.5516" logR="2.9021" logT="3.4501" Mc="0.8919" Menv="2.7885E-01" Spin="5.3613E-04" Z="?"/>
  <TrackPoint Age="202.7058" Stage="SAGB" M="1.4887" logL="4.5519" logR="2.9028" logT="3.4499" Mc="0.8919" Menv="2.6587E-01" Spin="5.1249E-04" Z="?"/>
  <TrackPoint Age="202.7061" Stage="SAGB" M="1.4738" logL="4.5522" logR="2.9034" logT="3.4496" Mc="0.8919" Menv="2.5324E-01" Spin="4.8937E-04" Z="?"/>
  <TrackPoint Age="202.7064" Stage="SAGB" M="1.4591" logL="4.5525" logR="2.9040" logT="3.4494" Mc="0.8919" Menv="2.4094E-01" Spin="4.6677E-04" Z="?"/>
  <TrackPoint Age="202.7067" Stage="SAGB" M="1.4445" logL="4.5528" logR="2.9046" logT="3.4492" Mc="0.8919" Menv="2.2899E-01" Spin="4.4467E-04" Z="?"/>
  <TrackPoint Age="202.7070" Stage="SAGB" M="1.4300" logL="4.5531" logR="2.9051" logT="3.4490" Mc="0.8919" Menv="2.1737E-01" Spin="4.2305E-04" Z="?"/>
  <TrackPoint Age="202.7073" Stage="SAGB" M="1.4157" logL="4.5534" logR="2.9056" logT="3.4488" Mc="0.8919" Menv="2.0609E-01" Spin="4.0191E-04" Z="?"/>
  <TrackPoint Age="202.7076" Stage="SAGB" M="1.4016" logL="4.5536" logR="2.9061" logT="3.4486" Mc="0.8919" Menv="1.9514E-01" Spin="3.8122E-04" Z="?"/>
  <TrackPoint Age="202.7078" Stage="SAGB" M="1.3875" logL="4.5539" logR="2.9065" logT="3.4485" Mc="0.8920" Menv="1.8451E-01" Spin="3.6099E-04" Z="?"/>
  <TrackPoint Age="202.7081" Stage="SAGB" M="1.3737" logL="4.5542" logR="2.9069" logT="3.4484" Mc="0.8920" Menv="1.7422E-01" Spin="3.4121E-04" Z="?"/>
  <TrackPoint Age="202.7084" Stage="SAGB" M="1.3599" logL="4.5545" logR="2.9073" logT="3.4483" Mc="0.8920" Menv="1.6425E-01" Spin="3.2186E-04" Z="?"/>
  <TrackPoint Age="202.7087" Stage="SAGB" M="1.3463" logL="4.5547" logR="2.9076" logT="3.4482" Mc="0.8920" Menv="1.5460E-01" Spin="3.0295E-04" Z="?"/>
  <TrackPoint Age="202.7090" Stage="SAGB" M="1.3329" logL="4.5550" logR="2.9079" logT="3.4481" Mc="0.8920" Menv="1.4528E-01" Spin="2.8447E-04" Z="?"/>
  <TrackPoint Age="202.7092" Stage="SAGB" M="1.3195" logL="4.5553" logR="2.9081" logT="3.4480" Mc="0.8920" Menv="1.3627E-01" Spin="2.6642E-04" Z="?"/>
  <TrackPoint Age="202.7095" Stage="SAGB" M="1.3063" logL="4.5555" logR="2.9083" logT="3.4480" Mc="0.8920" Menv="1.2758E-01" Spin="2.4880E-04" Z="?"/>
  <TrackPoint Age="202.7098" Stage="SAGB" M="1.2933" logL="4.5558" logR="2.9084" logT="3.4480" Mc="0.8921" Menv="1.1920E-01" Spin="2.3162E-04" Z="?"/>
  <TrackPoint Age="202.7100" Stage="SAGB" M="1.2804" logL="4.5560" logR="2.9085" logT="3.4480" Mc="0.8921" Menv="1.1114E-01" Spin="2.1489E-04" Z="?"/>
  <TrackPoint Age="202.7103" Stage="SAGB" M="1.2675" logL="4.5563" logR="2.9086" logT="3.4480" Mc="0.8921" Menv="1.0338E-01" Spin="1.9861E-04" Z="?"/>
  <TrackPoint Age="202.7106" Stage="SAGB" M="1.2549" logL="4.5565" logR="2.9086" logT="3.4481" Mc="0.8921" Menv="9.5935E-02" Spin="1.8279E-04" Z="?"/>
  <TrackPoint Age="202.7108" Stage="SAGB" M="1.2423" logL="4.5568" logR="2.9086" logT="3.4482" Mc="0.8921" Menv="8.8792E-02" Spin="1.6745E-04" Z="?"/>
  <TrackPoint Age="202.7111" Stage="SAGB" M="1.2299" logL="4.5570" logR="2.9085" logT="3.4483" Mc="0.8921" Menv="8.1952E-02" Spin="1.5261E-04" Z="?"/>
  <TrackPoint Age="202.7113" Stage="SAGB" M="1.2176" logL="4.5572" logR="2.9083" logT="3.4484" Mc="0.8921" Menv="7.5411E-02" Spin="1.3828E-04" Z="?"/>
  <TrackPoint Age="202.7116" Stage="SAGB" M="1.2054" logL="4.5575" logR="2.9081" logT="3.4486" Mc="0.8921" Menv="6.9168E-02" Spin="1.2449E-04" Z="?"/>
  <TrackPoint Age="202.7118" Stage="SAGB" M="1.1934" logL="4.5577" logR="2.9078" logT="3.4488" Mc="0.8921" Menv="6.3221E-02" Spin="1.1126E-04" Z="?"/>
  <TrackPoint Age="202.7121" Stage="SAGB" M="1.1814" logL="4.5579" logR="2.9075" logT="3.4490" Mc="0.8922" Menv="5.7565E-02" Spin="9.8621E-05" Z="?"/>
  <TrackPoint Age="202.7123" Stage="SAGB" M="1.1696" logL="4.5582" logR="2.9071" logT="3.4493" Mc="0.8922" Menv="5.2199E-02" Spin="8.6607E-05" Z="?"/>
  <TrackPoint Age="202.7125" Stage="SAGB" M="1.1579" logL="4.5584" logR="2.9066" logT="3.4496" Mc="0.8922" Menv="4.7119E-02" Spin="7.5249E-05" Z="?"/>
  <TrackPoint Age="202.7128" Stage="SAGB" M="1.1463" logL="4.5586" logR="2.9060" logT="3.4499" Mc="0.8922" Menv="4.2323E-02" Spin="6.4586E-05" Z="?"/>
  <TrackPoint Age="202.7130" Stage="SAGB" M="1.1349" logL="4.5589" logR="2.9053" logT="3.4503" Mc="0.8922" Menv="3.7807E-02" Spin="5.4653E-05" Z="?"/>
  <TrackPoint Age="202.7132" Stage="SAGB" M="1.1235" logL="4.5591" logR="2.9046" logT="3.4507" Mc="0.8922" Menv="3.3568E-02" Spin="4.5491E-05" Z="?"/>
  <TrackPoint Age="202.7135" Stage="SAGB" M="1.1123" logL="4.5593" logR="2.9037" logT="3.4512" Mc="0.8922" Menv="2.9603E-02" Spin="3.7134E-05" Z="?"/>
  <TrackPoint Age="202.7137" Stage="SAGB" M="1.1012" logL="4.5595" logR="2.9027" logT="3.4518" Mc="0.8922" Menv="2.5908E-02" Spin="2.9620E-05" Z="?"/>
  <TrackPoint Age="202.7139" Stage="SAGB" M="1.0902" logL="4.5597" logR="2.9016" logT="3.4524" Mc="0.8922" Menv="2.2478E-02" Spin="2.2977E-05" Z="?"/>
  <TrackPoint Age="202.7141" Stage="SAGB" M="1.0793" logL="4.5599" logR="2.9004" logT="3.4531" Mc="0.8923" Menv="1.9311E-02" Spin="1.7227E-05" Z="?"/>
  <TrackPoint Age="202.7144" Stage="SAGB" M="1.0685" logL="4.5601" logR="2.8990" logT="3.4538" Mc="0.8923" Menv="1.6401E-02" Spin="1.2380E-05" Z="?"/>
  <TrackPoint Age="202.7146" Stage="SAGB" M="1.0578" logL="4.5603" logR="2.8974" logT="3.4547" Mc="0.8923" Menv="1.3745E-02" Spin="8.4300E-06" Z="?"/>
  <TrackPoint Age="202.7148" Stage="SAGB" M="1.0472" logL="4.5605" logR="2.8955" logT="3.4556" Mc="0.8923" Menv="1.1336E-02" Spin="5.3495E-06" Z="?"/>
  <TrackPoint Age="202.7150" Stage="SAGB" M="1.0367" logL="4.5607" logR="2.8934" logT="3.4567" Mc="0.8923" Menv="9.1712E-03" Spin="3.0845E-06" Z="?"/>
  <TrackPoint Age="202.7152" Stage="SAGB" M="1.0264" logL="4.5609" logR="2.8910" logT="3.4580" Mc="0.8923" Menv="7.2444E-03" Spin="1.5502E-06" Z="?"/>
  <TrackPoint Age="202.7154" Stage="SAGB" M="1.0161" logL="4.5611" logR="2.8881" logT="3.4595" Mc="0.8923" Menv="5.5510E-03" Spin="6.2879E-07" Z="?"/>
  <TrackPoint Age="202.7156" Stage="SAGB" M="1.0059" logL="4.5613" logR="2.8848" logT="3.4612" Mc="0.8923" Menv="4.0862E-03" Spin="1.7266E-07" Z="?"/>
  <TrackPoint Age="202.7158" Stage="SAGB" M="0.9959" logL="4.5614" logR="2.8807" logT="3.4633" Mc="0.8923" Menv="2.8466E-03" Spin="1.5547E-08" Z="?"/>
  <TrackPoint Age="202.7160" Stage="SAGB" M="0.9859" logL="4.5616" logR="2.8756" logT="3.4659" Mc="0.8923" Menv="1.8300E-03" Spin="3.9100E-14" Z="?"/>
  <TrackPoint Age="202.7162" Stage="SAGB" M="0.9761" logL="4.5617" logR="2.8691" logT="3.4692" Mc="0.8923" Menv="1.0372E-03" Spin="5.4249E-14" Z="?"/>
  <TrackPoint Age="202.7164" Stage="SAGB" M="0.9663" logL="4.5618" logR="2.8603" logT="3.4736" Mc="0.8924" Menv="4.7209E-04" Spin="8.1320E-14" Z="?"/>
  <TrackPoint Age="202.7166" Stage="SAGB" M="0.9566" logL="4.5618" logR="2.8475" logT="3.4800" Mc="0.8924" Menv="1.3734E-04" Spin="1.3546E-13" Z="?"/>
  <TrackPoint Age="202.7168" Stage="SAGB" M="0.9471" logL="4.5616" logR="2.8274" logT="3.4900" Mc="0.8924" Menv="1.1647E-05" Spin="2.4733E-13" Z="?"/>
  <TrackPoint Age="202.7170" Stage="SAGB" M="0.9376" logL="4.5611" logR="2.7919" logT="3.5076" Mc="0.8924" Menv="1.0000E-10" Spin="4.0677E-13" Z="?"/>
  <TrackPoint Age="202.7172" Stage="SAGB" M="0.9282" logL="4.5596" logR="2.7182" logT="3.5441" Mc="0.8924" Menv="1.0000E-10" Spin="7.0858E-13" Z="?"/>
  <TrackPoint Age="202.7174" Stage="SAGB" M="0.9189" logL="4.5551" logR="2.5275" logT="3.6383" Mc="0.8924" Menv="1.0000E-10" Spin="2.2018E-12" Z="?"/>
  <TrackPoint Age="202.7176" Stage="SAGB" M="0.9098" logL="4.5348" logR="1.8687" logT="3.9626" Mc="0.8924" Menv="1.0000E-10" Spin="5.9683E-11" Z="?"/>
  <TrackPoint Age="202.7226" Stage="SAGB" M="0.9067" logL="4.5138" logR="1.2670" logT="4.2582" Mc="0.8926" Menv="1.0000E-10" Spin="9.7202E-10" Z="?"/>
  <TrackPoint Age="202.7256" Stage="SAGB" M="0.9049" logL="4.4875" logR="0.7717" logT="4.4993" Mc="0.8928" Menv="1.0000E-10" Spin="7.7615E-09" Z="?"/>
  <TrackPoint Age="202.7280" Stage="SAGB" M="0.9037" logL="4.4535" logR="0.3214" logT="4.7159" Mc="0.8929" Menv="1.0000E-10" Spin="3.2128E-08" Z="?"/>
  <TrackPoint Age="202.7301" Stage="SAGB" M="0.9027" logL="4.4099" logR="-0.0825" logT="4.9070" Mc="0.8930" Menv="1.0000E-10" Spin="6.9358E-08" Z="?"/>
  <TrackPoint Age="202.7322" Stage="SAGB" M="0.9018" logL="4.3549" logR="-0.4354" logT="5.0697" Mc="0.8931" Menv="1.0000E-10" Spin="1.0491E-07" Z="?"/>
  <TrackPoint Age="202.7343" Stage="SAGB" M="0.9011" logL="4.2877" logR="-0.7338" logT="5.2021" Mc="0.8932" Menv="1.0000E-10" Spin="1.3456E-07" Z="?"/>
  <TrackPoint Age="202.7364" Stage="SAGB" M="0.9005" logL="4.2081" logR="-0.9782" logT="5.3044" Mc="0.8933" Menv="1.0000E-10" Spin="1.5769E-07" Z="?"/>
  <TrackPoint Age="202.7387" Stage="SAGB" M="0.9001" logL="4.1177" logR="-1.1733" logT="5.3793" Mc="0.8934" Menv="1.0000E-10" Spin="1.7491E-07" Z="?"/>
  <TrackPoint Age="202.7412" Stage="SAGB" M="0.8997" logL="4.0186" logR="-1.3268" logT="5.4313" Mc="0.8935" Menv="1.0000E-10" Spin="1.8746E-07" Z="?"/>
  <TrackPoint Age="202.7439" Stage="SAGB" M="0.8994" logL="3.9128" logR="-1.4475" logT="5.4652" Mc="0.8937" Menv="1.0000E-10" Spin="2.8896E-07" Z="?"/>
  <TrackPoint Age="202.7468" Stage="SAGB" M="0.8992" logL="3.8013" logR="-1.5438" logT="5.4855" Mc="0.8938" Menv="1.0000E-10" Spin="4.1104E-07" Z="?"/>
  <TrackPoint Age="202.7500" Stage="SAGB" M="0.8991" logL="3.6836" logR="-1.6224" logT="5.4953" Mc="0.8940" Menv="1.0000E-10" Spin="5.4309E-07" Z="?"/>
  <TrackPoint Age="202.7535" Stage="SAGB" M="0.8990" logL="3.5578" logR="-1.6883" logT="5.4969" Mc="0.8941" Menv="1.0000E-10" Spin="6.8302E-07" Z="?"/>
  <TrackPoint Age="202.7574" Stage="SAGB" M="0.8989" logL="3.4207" logR="-1.7453" logT="5.4911" Mc="0.8943" Menv="1.0000E-10" Spin="8.3159E-07" Z="?"/>
  <TrackPoint Age="202.7616" Stage="SAGB" M="0.8988" logL="3.2673" logR="-1.7960" logT="5.4781" Mc="0.8946" Menv="1.0000E-10" Spin="9.9201E-07" Z="?"/>
  <TrackPoint Age="202.7666" Stage="SAGB" M="0.8988" logL="3.0828" logR="-1.8442" logT="5.4561" Mc="0.8948" Menv="1.0000E-10" Spin="1.1777E-06" Z="?"/>
  <TrackPoint Age="202.7716" Stage="SAGB" M="0.8988" logL="2.8916" logR="-1.8838" logT="5.4281" Mc="0.8951" Menv="1.0000E-10" Spin="1.3647E-06" Z="?"/>
  <TrackPoint Age="202.7766" Stage="SAGB" M="0.8988" logL="2.6936" logR="-1.9168" logT="5.3951" Mc="0.8954" Menv="1.0000E-10" Spin="1.5565E-06" Z="?"/>
  <TrackPoint Age="202.7816" Stage="SAGB" M="0.8987" logL="2.4913" logR="-1.9444" logT="5.3583" Mc="0.8956" Menv="1.0000E-10" Spin="1.7559E-06" Z="?"/>
  <TrackPoint Age="202.7866" Stage="SAGB" M="0.8987" logL="2.2894" logR="-1.9673" logT="5.3193" Mc="0.8959" Menv="1.0000E-10" Spin="1.9656E-06" Z="?"/>
  <TrackPoint Age="202.7916" Stage="SAGB" M="0.8987" logL="2.0947" logR="-1.9861" logT="5.2800" Mc="0.8962" Menv="1.0000E-10" Spin="2.1885E-06" Z="?"/>
  <TrackPoint Age="202.7966" Stage="SAGB" M="0.8987" logL="1.9150" logR="-2.0011" logT="5.2426" Mc="0.8964" Menv="1.0000E-10" Spin="2.4285E-06" Z="?"/>
  <TrackPoint Age="202.8016" Stage="SAGB" M="0.8987" logL="1.7573" logR="-2.0129" logT="5.2090" Mc="0.8967" Menv="1.0000E-10" Spin="2.6905E-06" Z="?"/>
  <TrackPoint Age="202.8066" Stage="SAGB" M="0.8987" logL="1.6275" logR="-2.0216" logT="5.1810" Mc="0.8970" Menv="1.0000E-10" Spin="2.9819E-06" Z="?"/>
  <TrackPoint Age="202.8116" Stage="SAGB" M="0.8987" logL="1.5283" logR="-2.0279" logT="5.1593" Mc="0.8973" Menv="1.0000E-10" Spin="3.3132E-06" Z="?"/>
  <TrackPoint Age="202.8166" Stage="SAGB" M="0.8987" logL="1.4595" logR="-2.0321" logT="5.1442" Mc="0.8976" Menv="1.0000E-10" Spin="3.6997E-06" Z="?"/>
  <TrackPoint Age="202.8216" Stage="SAGB" M="0.8987" logL="1.4176" logR="-2.0346" logT="5.1350" Mc="0.8979" Menv="1.0000E-10" Spin="4.1652E-06" Z="?"/>
  <TrackPoint Age="202.8266" Stage="SAGB" M="0.8987" logL="1.3969" logR="-2.0359" logT="5.1305" Mc="0.8982" Menv="1.0000E-10" Spin="4.7473E-06" Z="?"/>
  <TrackPoint Age="202.8316" Stage="SAGB" M="0.8987" logL="1.3904" logR="-2.0364" logT="5.1291" Mc="0.8985" Menv="1.0000E-10" Spin="5.5101E-06" Z="?"/>
  <TrackPoint Age="202.8354" Stage="ONWD" M="0.8987" logL="1.3899" logR="-2.0366" logT="5.1290" Mc="0.8987" Menv="1.0000E-10" Spin="6.2704E-06" Z="?"/>
  <TrackPoint Age="202.9354" Stage="ONWD" M="0.8987" logL="1.0347" logR="-2.0366" logT="5.0402" Mc="0.8987" Menv="1.0000E-10" Spin="6.2704E-06" Z="?"/>
  <TrackPoint Age="203.9354" Stage="ONWD" M="0.8987" logL="0.1165" logR="-2.0366" logT="4.8107" Mc="0.8987" Menv="1.0000E-10" Spin="6.2704E-06" Z="?"/>
  <TrackPoint Age="213.9354" Stage="ONWD" M="0.8987" logL="-1.0282" logR="-2.0366" logT="4.5245" Mc="0.8987" Menv="1.0000E-10" Spin="6.2704E-06" Z="?"/>
  <TrackPoint Age="313.9354" Stage="ONWD" M="0.8987" logL="-2.2045" logR="-2.0366" logT="4.2304" Mc="0.8987" Menv="1.0000E-10" Spin="6.2704E-06" Z="?"/>
  <TrackPoint Age="813.9354" Stage="ONWD" M="0.8987" logL="-3.0778" logR="-2.0366" logT="4.0121" Mc="0.8987" Menv="1.0000E-10" Spin="6.2704E-06" Z="?"/>
  <TrackPoint Age="1313.9354" Stage="ONWD" M="0.8987" logL="-3.3841" logR="-2.0366" logT="3.9355" Mc="0.8987" Menv="1.0000E-10" Spin="6.2704E-06" Z="?"/>
  <TrackPoint Age="1813.9354" Stage="ONWD" M="0.8987" logL="-3.5745" logR="-2.0366" logT="3.8879" Mc="0.8987" Menv="1.0000E-10" Spin="6.2704E-06" Z="?"/>
  <TrackPoint Age="2313.9353" Stage="ONWD" M="0.8987" logL="-3.7131" logR="-2.0366" logT="3.8533" Mc="0.8987" Menv="1.0000E-10" Spin="6.2704E-06" Z="?"/>
  <TrackPoint Age="2813.9353" Stage="ONWD" M="0.8987" logL="-3.8220" logR="-2.0366" logT="3.8261" Mc="0.8987" Menv="1.0000E-10" Spin="6.2704E-06" Z="?"/>
  <TrackPoint Age="3313.9353" Stage="ONWD" M="0.8987" logL="-3.9118" logR="-2.0366" logT="3.8036" Mc="0.8987" Menv="1.0000E-10" Spin="6.2704E-06" Z="?"/>
  <TrackPoint Age="3813.9353" Stage="ONWD" M="0.8987" logL="-3.9881" logR="-2.0366" logT="3.7845" Mc="0.8987" Menv="1.0000E-10" Spin="6.2704E-06" Z="?"/>
  <TrackPoint Age="4313.9355" Stage="ONWD" M="0.8987" logL="-4.0546" logR="-2.0366" logT="3.7679" Mc="0.8987" Menv="1.0000E-10" Spin="6.2704E-06" Z="?"/>
  <TrackPoint Age="4813.9355" Stage="ONWD" M="0.8987" logL="-4.1134" logR="-2.0366" logT="3.7532" Mc="0.8987" Menv="1.0000E-10" Spin="6.2704E-06" Z="?"/>
  <TrackPoint Age="5313.9355" Stage="ONWD" M="0.8987" logL="-4.1662" logR="-2.0366" logT="3.7400" Mc="0.8987" Menv="1.0000E-10" Spin="6.2704E-06" Z="?"/>
  <TrackPoint Age="5813.9355" Stage="ONWD" M="0.8987" logL="-4.2140" logR="-2.0366" logT="3.7281" Mc="0.8987" Menv="1.0000E-10" Spin="6.2704E-06" Z="?"/>
  <TrackPoint Age="6313.9355" Stage="ONWD" M="0.8987" logL="-4.2577" logR="-2.0366" logT="3.7171" Mc="0.8987" Menv="1.0000E-10" Spin="6.2704E-06" Z="?"/>
  <TrackPoint Age="6813.9355" Stage="ONWD" M="0.8987" logL="-4.2980" logR="-2.0366" logT="3.7070" Mc="0.8987" Menv="1.0000E-10" Spin="6.2704E-06" Z="?"/>
  <TrackPoint Age="7313.9355" Stage="ONWD" M="0.8987" logL="-4.3354" logR="-2.0366" logT="3.6977" Mc="0.8987" Menv="1.0000E-10" Spin="6.2704E-06" Z="?"/>
  <TrackPoint Age="7813.9355" Stage="ONWD" M="0.8987" logL="-4.3702" logR="-2.0366" logT="3.6890" Mc="0.8987" Menv="1.0000E-10" Spin="6.2704E-06" Z="?"/>
  <TrackPoint Age="8313.9355" Stage="ONWD" M="0.8987" logL="-4.4028" logR="-2.0366" logT="3.6808" Mc="0.8987" Menv="1.0000E-10" Spin="6.2704E-06" Z="?"/>
  <TrackPoint Age="8813.9355" Stage="ONWD" M="0.8987" logL="-4.4335" logR="-2.0366" logT="3.6732" Mc="0.8987" Menv="1.0000E-10" Spin="6.2704E-06" Z="?"/>
  <TrackPoint Age="9313.9355" Stage="ONWD" M="0.8987" logL="-4.4906" logR="-2.0366" logT="3.6589" Mc="0.8987" Menv="1.0000E-10" Spin="6.2704E-06" Z="?"/>
  <TrackPoint Age="9813.9355" Stage="ONWD" M="0.8987" logL="-4.6410" logR="-2.0366" logT="3.6213" Mc="0.8987" Menv="1.0000E-10" Spin="6.2704E-06" Z="?"/>
  <TrackPoint Age="10313.9355" Stage="ONWD" M="0.8987" logL="-4.7837" logR="-2.0366" logT="3.5856" Mc="0.8987" Menv="1.0000E-10" Spin="6.2704E-06" Z="?"/>
  <TrackPoint Age="10813.9355" Stage="ONWD" M="0.8987" logL="-4.9195" logR="-2.0366" logT="3.5517" Mc="0.8987" Menv="1.0000E-10" Spin="6.2704E-06" Z="?"/>
  <TrackPoint Age="11313.9355" Stage="ONWD" M="0.8987" logL="-5.0491" logR="-2.0366" logT="3.5193" Mc="0.8987" Menv="1.0000E-10" Spin="6.2704E-06" Z="?"/>
  <TrackPoint Age="11813.9355" Stage="ONWD" M="0.8987" logL="-5.1730" logR="-2.0366" logT="3.4883" Mc="0.8987" Menv="1.0000E-10" Spin="6.2704E-06" Z="?"/>
  <TrackPoint Age="12313.9355" Stage="ONWD" M="0.8987" logL="-5.2916" logR="-2.0366" logT="3.4586" Mc="0.8987" Menv="1.0000E-10" Spin="6.2704E-06" Z="?"/>
  <TrackPoint Age="12813.9355" Stage="ONWD" M="0.8987" logL="-5.4055" logR="-2.0366" logT="3.4302" Mc="0.8987" Menv="1.0000E-10" Spin="6.2704E-06" Z="?"/>
  <TrackPoint Age="13313.9355" Stage="ONWD" M="0.8987" logL="-5.5149" logR="-2.0366" logT="3.4028" Mc="0.8987" Menv="1.0000E-10" Spin="6.2704E-06" Z="?"/>
  <TrackPoint Age="13800.0000" Stage="ONWD" M="0.8987" logL="-5.6174" logR="-2.0366" logT="3.3772" Mc="0.8987" Menv="1.0000E-10" Spin="6.2704E-06" Z="?"/>
</Track>
